Workbook
Name _GoBack: #REF!
Name Excel_BuiltIn_Print_Titles_13: '[1]extra work elec bill '!#REF!

Sheet CWI Summary
A1: Summary For Ichalkarnji, Kolhapur
A3: Address | B3: HDFC Bank Ltd. Upper Ground Floor & first floor ,12/215,Bungalow Road, Ichalkarnji,Tal- Hatkanagale,Dist -Kolhapur - 416115.
A4: Contractor | B4: M/s. Teamswift Projects Pvt Ltd
A5: Area | B5: 2,280 Sqft
A6: LOC, Code | B6: 0736
A7: PO No | B7: CPC/014849/25-26
A8: FINAL BILL SUMMARY
A9: Sr. No | B9: Particulars | C9: AS per WO | D9: As per CWI | E9: Excess | F9: Saving | G9: Total
A10: I | B10: Civil & related works | C10: =BOQ!$F$200 -> 1504620 | D10: =BOQ!$I$200 -> 1444213.2 | E10: =BOQ!L200 -> 102419.15 | F10: =BOQ!M200 -> -162825.93 | G10: =BOQ!N200 -> -60406.78
A11: II | B11: POP and false ceiling work | C11: =BOQ!$F$217 -> 324120 | D11: =BOQ!$I$217 -> 295074.12 | E11: =BOQ!L217 -> 21427.64 | F11: =BOQ!M217 -> -50473.52 | G11: =BOQ!N217 -> -29045.88
A12: III | B12: Carpentry and Interior work | C12: =BOQ!$F$456 -> 2147140 | D12: =BOQ!$I$456 -> 1999427.6 | E12: =BOQ!L456 -> 364478.61 | F12: =BOQ!M456 -> -512191.02 | G12: =BOQ!N456 -> -147712.41
A13: IV | B13: Painting works | C13: =BOQ!$F$481 -> 69930 | D13: =BOQ!$I$481 -> 79262 | E13: =BOQ!L481 -> 31362.25 | F13: =BOQ!M481 -> -22030.25 | G13: =BOQ!N481 -> 9332
A14: V | B14: Rolling Shutter and MS Work | C14: =BOQ!$F$509 -> 28800 | D14: =BOQ!$I$509 -> 0 | E14: =BOQ!L509 -> 0 | F14: =BOQ!M509 -> -28800 | G14: =BOQ!N509 -> -28800
A15: VI | B15: Electrification and Allied Work | C15: =BOQ!$F$1148 -> 1106859 | D15: =BOQ!$I$1148 -> 793654.56 | E15: =BOQ!L1148 -> 105439 | F15: =BOQ!M1148 -> -418643.44 | G15: =BOQ!N1148 -> -313204.44
A16: VII | B16: Additional Work | C16: =BOQ!$F$1163 -> 0 | D16: =BOQ!$I$1163 -> 162810.6 | E16: =BOQ!L1163 -> 162810.6 | F16: =BOQ!M1163 -> 0 | G16: =BOQ!N1163 -> 162810.6
A17: A | B17: TOTAL | C17: =SUM(C10:C16) -> 5181469 | D17: =SUM(D10:D16) -> 4774442.1 | E17: =SUM(E10:E16) -> 787937.25 | F17: =SUM(F10:F16) -> -1194964.2 | G17: =SUM(G10:G16) -> -407026.91
A18: TAXES | B18: TAXES:
B19: Taxes as applicable (pl indicate applicable taxes)
A20: a) | B20: CGST @ 9% | C20: =C17*9% -> 466332.21 | D20: =D17*9% -> 429699.79 | E20: =E17*9% -> 70914.352 | F20: =F17*9% -> -107546.77 | G20: =G17*9% -> -36632.422
A21: b) | B21: SGST @ 9% | C21: =C17*9% -> 466332.21 | D21: =D17*9% -> 429699.79 | E21: =E17*9% -> 70914.352 | F21: =F17*9% -> -107546.77 | G21: =G17*9% -> -36632.422
A22: c)
A24: B | B24: Total | C24: =SUM(C19:C23) -> 932664.42 | D24: =SUM(D19:D23) -> 859399.58 | E24: =SUM(E20:E23) -> 141828.7 | F24: =SUM(F19:F23) -> -215093.55 | G24: =SUM(G19:G23) -> -73264.844
A26: (A + B) | B26: Grand Total (incl. taxes) | C26: =C17+C24 -> 6114133.4 | D26: =D17+D24 -> 5633841.7 | E26: =SUM(E19:E25) -> 283657.41 | F26: =SUM(F19:F25) -> -430187.1 | G26: =SUM(G19:G25) -> -146529.69

Sheet Extracted Data
A1: U. Code | B1: Sub Category | C1: Nature of Works | D1: Particulars | E1: Rate | F1: As per CWI (Qty) | G1: As per CWI (Amount) | H1: Rate per sq.feet | I1: Unit
A2: Sr. No | B2: Others | C2: Others/Uncategorized | D2: Particulars | E2: 0 | F2: 0 | G2: 0 | H2: 0 | I2: Unit
A3: I | B3: Others | C3: Others/Uncategorized | D3: CIVIL & RELATED WORKS | E3: 0 | F3: 0 | G3: 0 | H3: 0
A4: 1 | B4: Others | C4: Others/Uncategorized | D4: Demolition / Clearing Works | E4: 0 | F4: 0 | G4: 0 | H4: 0
A5: a | B5: Others | C5: Others/Uncategorized | D5: Dismantling/Demolishing the following and carting away the debris from the site and unloading at a approved location as per statutory rules and regulations. | E5: 0 | F5: 0 | G5: 0 | H5: 0
A6: i | B6: Others | C6: Others/Uncategorized | D6: Dismantling of existing brickwork | E6: 12 | F6: 0 | G6: 0 | H6: 0 | I6: Sq.ft
A7: ii | B7: POP Punning | C7: POP & FALSE CEILING WORKS | D7: Dismantling of existing dado tiles without plaster | E7: 11 | F7: 932.39 | G7: 10256.29 | H7: 4.5 | I7: Sq.ft
A8: iii | B8: Partition | C8: CARPENTRY AND INTERIOR WORKS | D8: Dismantling of existing plaster | E8: 11 | F8: 459.73 | G8: 5057.03 | H8: 2.22 | I8: Sq.ft
A9: iv | B9: PAINTING WORKS | C9: PAINTING WORKS | D9: Existing flooring including bedding material & PCC/IPS. | E9: 16 | F9: 540.83 | G9: 8653.28 | H9: 3.8 | I9: Sq.ft
A10: v | B10: ROLLING SHUTTER AND MS WORK | C10: ROLLING SHUTTER AND MS WORK | D10: Existing Doors / Windows | E10: 381 | F10: 16 | G10: 6096 | H10: 2.67 | I10: Nos.
A11: vi | B11: ELECTRIFICATION AND ALLIED WORKS | C11: ELECTRIFICATION AND ALLIED WORKS | D11: Dismantling of existing Sanitary wares & Plumbing Fittings | E11: 1199 | F11: 0 | G11: 0 | H11: 0 | I11: Nos.
A12: vii | B12: ELECTRIFICATION AND ALLIED WORKS | C12: ELECTRIFICATION AND ALLIED WORKS | D12: Existing Rolling Shutter , Safety door, collapsible door etc. | E12: 11 | F12: 0 | G12: 0 | H12: 0 | I12: Sq.ft
A13: viii | B13: ELECTRIFICATION AND ALLIED WORKS | C13: ELECTRIFICATION AND ALLIED WORKS | D13: Existing Electrical fittings and fixtures | E13: 3 | F13: 0 | G13: 0 | H13: 0 | I13: Sq.ft
A14: ix | B14: ELECTRIFICATION AND ALLIED WORKS | C14: ELECTRIFICATION AND ALLIED WORKS | D14: Dismantling of existing wooden & aluminum partitions | E14: 10 | F14: 0 | G14: 0 | H14: 0 | I14: Sq.ft
A15: x | B15: ELECTRIFICATION AND ALLIED WORKS | C15: ELECTRIFICATION AND ALLIED WORKS | D15: Miscellaneous items such as false ceilings. | E15: 11 | F15: 0 | G15: 0 | H15: 0 | I15: Sq.ft
A16: xi | B16: ELECTRIFICATION AND ALLIED WORKS | C16: ELECTRIFICATION AND ALLIED WORKS | D16: Shifting /Dismantling existing furniture items (For renovation projects only) | E16: 487 | F16: 0 | G16: 0 | H16: 0 | I16: Nos.
A17: xii | B17: ELECTRIFICATION AND ALLIED WORKS | C17: ELECTRIFICATION AND ALLIED WORKS | D17: Dismantling of existing RCC 6 "/ 9" thk wall. | E17: 84 | F17: 2 | G17: 168 | H17: 0.07 | I17: Sq.ft
A18: 2 | B18: ELECTRIFICATION AND ALLIED WORKS | C18: ELECTRIFICATION AND ALLIED WORKS | D18: Construction of Masonry Walls | E18: 0 | F18: 0 | G18: 0 | H18: 0
A19: a | B19: ELECTRIFICATION AND ALLIED WORKS | C19: ELECTRIFICATION AND ALLIED WORKS | D19: Providing and erecting 115 mm thk , Half brick wall (first class bricks) in cement and sand mortar 1:3 with flush joint complete with material, labour, scaffolding, curing etc. The rate to include Appling chicken mesh at RCC to brickwork joints wherever required and RCC stiffener at every 1 meter intervals in 1:2:4 concrete. (Excluding plastering). The work to include cost for lintels / sills in RCC required for Doors , windows, openings etc. | E19: 114 | F19: 0 | G19: 0 | H19: 0 | I19: Sq.ft
A20: b | B20: ELECTRIFICATION AND ALLIED WORKS | C20: ELECTRIFICATION AND ALLIED WORKS | D20: Same as 2(a) but 230mm thk ( Single brick wall) | E20: 150 | F20: 0 | G20: 0 | H20: 0 | I20: Sq.ft
A21: c | B21: ELECTRIFICATION AND ALLIED WORKS | C21: ELECTRIFICATION AND ALLIED WORKS | D21: Do-do as 2(a) above but 100mm thk siporex / AAC / Aerocon / light weight block wall (Green Pro certified make approved by bank or CPC team as exception/ Refer make and model sheet,aerocon blocks) | E21: 124 | F21: 0 | G21: 0 | H21: 0 | I21: Sq.ft
A22: d | B22: ELECTRIFICATION AND ALLIED WORKS | C22: ELECTRIFICATION AND ALLIED WORKS | D22: Do-do as 2(a) above but 150mm thk siporex / AAC / Aerocon / light weight block wall (Green Pro certified make approved by bank or CPC team as exception/ Refer make and model sheet,aerocon blocks) | E22: 129 | F22: 851.4 | G22: 109830.6 | H22: 48.17 | I22: Sq.ft
A23: 3 | B23: ELECTRIFICATION AND ALLIED WORKS | C23: ELECTRIFICATION AND ALLIED WORKS | D23: R.C.C Works | E23: 0 | F23: 0 | G23: 0 | H23: 0
A24: a | B24: ELECTRIFICATION AND ALLIED WORKS | C24: ELECTRIFICATION AND ALLIED WORKS | D24: R.C.C work :Providing & casting in-situ reinforced cement concrete 225 mm thick for wall/columns/ as per details/ drawings/ design( The rate to include cost of re-baring/Hilti/drilling and joining with existing beam or lintel including shuttering, steel , concrete, inserts, cutout for ventilator, hacking, curing, bonding chemical / slurry all complete, design and certification from structural consultant. Grade of concrete to be considered shall be M25 & steel to be considered as 12mm dia tor steel @150mm c/c both way in two layers staggered by 75mm in both directions. The thickness of walls to be 225 mm without plaster. 300mm x300mm RCC column to be provided near the strong room door for mounting strong room door. | E24: 444 | F24: 0 | G24: 0 | H24: 0 | I24: Sq.ft
A25: b | B25: ELECTRIFICATION AND ALLIED WORKS | C25: ELECTRIFICATION AND ALLIED WORKS | D25: Do-do as 3(a) above but Ready mix concrete (Green Pro certified make approved by bank or CPC team as exception/ Refer make and model sheet,RMC) | E25: 699 | F25: 0 | G25: 0 | H25: 0 | I25: Sq.ft
A26: c | B26: ELECTRIFICATION AND ALLIED WORKS | C26: ELECTRIFICATION AND ALLIED WORKS | D26: Similar to above but for Floor slab with single layer of steel comprising 12mm dia @150 mm c/c and concrete jointing compound to be provided in case the premises is located on first floor and floor below does not belong to the bank. | E26: 198 | F26: 0 | G26: 0 | H26: 0 | I26: Sq.ft
A27: d | B27: ELECTRIFICATION AND ALLIED WORKS | C27: ELECTRIFICATION AND ALLIED WORKS | D27: Do-do as 3(c) above but Ready mix concrete (Green Pro certified make approved by bank or CPC team as exception/ Refer make and model sheet,RMC) | E27: 330 | F27: 0 | G27: 0 | H27: 0 | I27: Sq.ft
A28: e | B28: ELECTRIFICATION AND ALLIED WORKS | C28: ELECTRIFICATION AND ALLIED WORKS | D28: Similar to above but for Floor slab with double layer of steel comprising of 12 mm dia @ 150 mm c/c Mesh on both ways staggered by 75mm and concrete jointing compound to be provided in case the premises is located on first floor and floor below does not belong to the bank. | E28: 336 | F28: 0 | G28: 0 | H28: 0 | I28: Sq.ft
A29: f | B29: ELECTRIFICATION AND ALLIED WORKS | C29: ELECTRIFICATION AND ALLIED WORKS | D29: Do-do as 3(f) above but Ready mix concrete (Green Pro certified make approved by bank or CPC team as exception/ Refer make and model sheet,RMC) | E29: 453 | F29: 0 | G29: 0 | H29: 0 | I29: Sq.ft
A30: g | B30: ELECTRIFICATION AND ALLIED WORKS | C30: ELECTRIFICATION AND ALLIED WORKS | D30: Similar to above but without concrete (ceiling reinforcement Mesh to be provided in case upper floor does not belong to the bank) | E30: 129 | F30: 0 | G30: 0 | H30: 0 | I30: Sq.ft
A31: i | B31: ELECTRIFICATION AND ALLIED WORKS | C31: ELECTRIFICATION AND ALLIED WORKS | D31: Do-do as 3(g) above but Ready mix concrete (Green Pro certified make approved by bank or CPC team as exception/ Refer make and model sheet,RMC) | E31: 389 | F31: 0 | G31: 0 | H31: 0 | I31: Sq.ft
A32: j | B32: ELECTRIFICATION AND ALLIED WORKS | C32: ELECTRIFICATION AND ALLIED WORKS | D32: Similar to item 3(c) i.e. 6mm MS plate instead of reinforcement mesh for wall cladding. Including necessary MS framework. Complete as directed. | E32: 468 | F32: 0 | G32: 0 | H32: 0 | I32: Sq.ft
A33: k | B33: ELECTRIFICATION AND ALLIED WORKS | C33: ELECTRIFICATION AND ALLIED WORKS | D33: Fixing in place of Strong Room Door by providing necessary grouting in the floor and proper support. The vendor should ensure that the door is fixed in plumb. | E33: 8559 | F33: 0 | G33: 0 | H33: 0 | I33: Job
A34: l | B34: ELECTRIFICATION AND ALLIED WORKS | C34: ELECTRIFICATION AND ALLIED WORKS | D34: Fixing in place of Ventilator by providing necessary grouting in the floor and proper support. The vendor should ensure that the door is fixed in plumb. | E34: 5720 | F34: 0 | G34: 0 | H34: 0 | I34: Job
A35: 4 | B35: ELECTRIFICATION AND ALLIED WORKS | C35: ELECTRIFICATION AND ALLIED WORKS | D35: Plaster | E35: 0 | F35: 0 | G35: 0 | H35: 0
A36: a | B36: ELECTRIFICATION AND ALLIED WORKS | C36: ELECTRIFICATION AND ALLIED WORKS | D36: P/A 1:4 cement plaster(Green Pro certified make approved by bank or CPC team as exception/ Refer make and model sheet,cement) with waterproofing compound to brick/RCC work including scaffolding in single coat of minimum 12 mm thick finished to receive Plaster of Paris levelling coat. | E36: 46 | F36: 2317.13 | G36: 106587.98 | H36: 46.75 | I36: Sq.ft
A37: b | B37: ELECTRIFICATION AND ALLIED WORKS | C37: ELECTRIFICATION AND ALLIED WORKS | D37: External Plaster in 1:3 with waterproofing compound to brick/RCC work up to 25mm thk including cost of scaffolding up to 20'.( Prior approval of Bank required) (Green Pro certified make approved by bank or CPC team as exception/ Refer make and model sheet,cement) | E37: 62 | F37: 0 | G37: 0 | H37: 0 | I37: Sq.ft
A38: 5 | B38: ELECTRIFICATION AND ALLIED WORKS | C38: ELECTRIFICATION AND ALLIED WORKS | D38: Waterproofing treatment | E38: 0 | F38: 0 | G38: 0 | H38: 0
A39: a | B39: ELECTRIFICATION AND ALLIED WORKS | C39: ELECTRIFICATION AND ALLIED WORKS | D39: Providing & appling water proofing treatement by Mixing and applying two coats of ready-to-use acrylic polymer based waterproofing component on modified cement base of approved make to a thickness of 2 mm over the bottom and sides of toilet and pantry slabs, including preparation of surface, finishing, curing etc. all complete at all levels as per manufacturer's specifications and as directed. | E39: 45 | F39: 285.08 | G39: 12828.6 | H39: 5.63 | I39: Sq.ft
A40: 6 | B40: ELECTRIFICATION AND ALLIED WORKS | C40: ELECTRIFICATION AND ALLIED WORKS | D40: Brick Bat Coba | E40: 0 | F40: 0 | G40: 0 | H40: 0
A41: a | B41: ELECTRIFICATION AND ALLIED WORKS | C41: ELECTRIFICATION AND ALLIED WORKS | D41: Proving and Laying brick bat coba up to 150mm thk in 1:4 cement mortar incl. of necessary slope towards nahni trap, over waterproofing course including finishing the top surface with water proofing compound to receive the floor tiles as per India Waterproofing Co. Measurements of floor area shall only be considered for said works.(Toilet area) | E41: 88 | F41: 109.28 | G41: 9616.64 | H41: 4.22 | I41: Sq.ft
A42: 7 | B42: ELECTRIFICATION AND ALLIED WORKS | C42: ELECTRIFICATION AND ALLIED WORKS | D42: Plain Cement Concrete | E42: 0 | F42: 0 | G42: 0 | H42: 0
A43: a | B43: ELECTRIFICATION AND ALLIED WORKS | C43: ELECTRIFICATION AND ALLIED WORKS | D43: P/E Plain cement concrete (Green Pro certified make approved by bank or CPC team as exception/ Refer make and model sheet,cement section) of grade M -10 ( 1:3:6 ) including shuttering for levelling course for flooring within the Bank Premise. The thickness may vary from 75mm to 125 mm as per requirement. (As per site condition - Prior approval of Bank required) | E43: 50 | F43: 534.5 | G43: 26725 | H43: 11.72 | I43: Sq.ft
A44: b | B44: ELECTRIFICATION AND ALLIED WORKS | C44: ELECTRIFICATION AND ALLIED WORKS | D44: Same as 7(A) but for depth upto 250 mm | E44: 105 | F44: 0 | G44: 0 | H44: 0 | I44: Sq.ft
A45: c | B45: ELECTRIFICATION AND ALLIED WORKS | C45: ELECTRIFICATION AND ALLIED WORKS | D45: Do-do as 7(a) above but Ready mix concrete (Green Pro certified make approved by bank or CPC team as exception/ Refer make and model sheet,RMC) | E45: 72 | F45: 0 | G45: 0 | H45: 0 | I45: Sq.ft
A46: d | B46: ELECTRIFICATION AND ALLIED WORKS | C46: ELECTRIFICATION AND ALLIED WORKS | D46: Do-do as 7(b) above but Ready mix concrete (Green Pro certified make approved by bank or CPC team as exception/ Refer make and model sheet,RMC) | E46: 139 | F46: 0 | G46: 0 | H46: 0 | I46: Sq.ft
A47: e | B47: ELECTRIFICATION AND ALLIED WORKS | C47: ELECTRIFICATION AND ALLIED WORKS | D47: Similar to above but for exterior works (As per site condition - Prior approval of Bank required) | E47: 64 | F47: 0 | G47: 0 | H47: 0 | I47: Sq.ft
A48: f | B48: ELECTRIFICATION AND ALLIED WORKS | C48: ELECTRIFICATION AND ALLIED WORKS | D48: Do-do as 7(e) above but Ready mix concrete (Green Pro certified make approved by bank or CPC team as exception/ Refer make and model sheet,RMC) | E48: 80 | F48: 0 | G48: 0 | H48: 0 | I48: Sq.ft
A49: g | B49: ELECTRIFICATION AND ALLIED WORKS | C49: ELECTRIFICATION AND ALLIED WORKS | D49: Providing and laying cement concrete flooring 40 - 50 mm thick , C.M. 1:3 laid to proper level and slope cost should including compaction as directed and curing complete in all respect. (As per site condition - Prior approval of Bank required)(Green Pro certified make approved by bank or CPC team as exception/ Refer make and model sheet,cement section) | E49: 38 | F49: 0 | G49: 0 | H49: 0 | I49: Sq.ft
A50: 8 | B50: ELECTRIFICATION AND ALLIED WORKS | C50: ELECTRIFICATION AND ALLIED WORKS | D50: Drywall Panel | E50: 0 | F50: 0 | G50: 0 | H50: 0
A51: a | B51: ELECTRIFICATION AND ALLIED WORKS | C51: ELECTRIFICATION AND ALLIED WORKS | D51: Providing and fixing of Solid Dry Wall Panel 75mm thick of size 2400/2700/3000mm in length and 600mm width certified by Green Building council having a unique tongue and groove jointing system. The panels are made of two fibre reinforced cement sheets enclosing a light weight aerated concrete core composed of cement, fly ash and other binders. Density is 720~780kg/cum, panel has Axial load carrying capacity min 83 KN/m with 2.5 times factor safety as per test method of ASTM -E-72:98 . These panels need to meet Uniformly distributed load (Bending load 80 -95kg/sqm & modulus of rupture 40-58kg/sqcm) as per test method ASTM-E-72:98 & IS 2380 Part 4. Thermal Conductivity typical K value - 0.17 ~0.21 W/m K, having a fire rating of 120 minutes as per BS 476 part 20-22 and sound transmission coefficient 36~40 as per IS 9901 (part 1) 1981 The wall panels to be installed with G.I Floor Channel : 14 x 75 x 25 mm size of 1 mm thick at bottom and 38 X75X 38 mm size with 1mm thickness at top. Tongue and Groove joints will be joined with elastomeric cementitious highly polymerized jointing compound as per manufacturer’s recommendation. Non-woven Self-adhesive glass fiber / fiber mesh tape in sufficient width to be applied to reinforce the exposed skin of jointing system. Jointing compound to be applied on joint finally to make good . Rate by the vendor to include scaffolding, lifting charges and jointing material, wastages etc. as a complete item of work excluding finishing etc. The installation will be done as per specification, drawing and as directed by EIC/consultant. All work to be done by certified installer with proper supervision following WMS and as per instruction of Engineering in charge. (Ideal for Server room , Solid Partition, Store rooms ) Approved Brands : HIL Limited , Visaka (Vnext) , Everest Panel) (Green Pro certified make approved by bank or CPC team as exception/ Refer make and model sheet, Aerocon Panel) | E51: 160 | F51: 0 | G51: 0 | H51: 0 | I51: Sq.ft
A52: b | B52: ELECTRIFICATION AND ALLIED WORKS | C52: ELECTRIFICATION AND ALLIED WORKS | D52: Do-do as 8(a) above but 100mm thk (Green Pro certified make approved by bank or CPC team as exception/ Refer make and model sheet, Aerocon Panel) | E52: 254 | F52: 0 | G52: 0 | H52: 0 | I52: Sq.ft
A53: 9 | B53: ELECTRIFICATION AND ALLIED WORKS | C53: ELECTRIFICATION AND ALLIED WORKS | D53: Flooring | E53: 0 | F53: 0 | G53: 0 | H53: 0
A54: a | B54: ELECTRIFICATION AND ALLIED WORKS | C54: ELECTRIFICATION AND ALLIED WORKS | D54: Vitrified Tile Flooring | E54: 0 | F54: 0 | G54: 0 | H54: 0
A55: i | B55: ELECTRIFICATION AND ALLIED WORKS | C55: ELECTRIFICATION AND ALLIED WORKS | D55: Vitrified Tile Flooring - Proving and Laying 1000mm x 1000mm / 800mm X 800 mm Vitrified floor tiles (Green Pro certified make approved by bank or CPC team as exception/ Refer make and model sheet,vitrified floor tiles) over a 75 mm thk cement mortar (Green Pro certified make approved by bank or CPC team as exception/ Refer make and model sheet,cement section) bedding (1: 4) as per the design. The joints shall be kept up to 4 mm and filled with epoxy grouting of approved shade. (Basic cost of tile up to up to Rs. 110/-Sq. ft). | E55: 152 | F55: 2009.78 | G55: 305486.56 | H55: 133.99 | I55: Sq.ft
A56: ii | B56: POP Punning | C56: POP & FALSE CEILING WORKS | D56: Similar to above but for providing and fixing 75mm high skirting/border. | E56: 66 | F56: 86.45 | G56: 5705.7 | H56: 2.5 | I56: R.ft
A57: iii | B57: Partition | C57: CARPENTRY AND INTERIOR WORKS | D57: Proving and Laying 600mm x 600mm anti-skid and Anti-dust Vitrified floor tiles for Toilet floors with a 75 mm thk cement mortar (Green Pro certified make approved by bank or CPC team as exception/ Refer make and model sheet,cement section) bedding (1: 4) as per the design including colour cement in joint to matching shade. The joints shall be kept as thin as possible should not exceeding 1 mm. (Basic cost of tile upto Rs. 60 /-Sq. ft). ( For server room, store, pantry, toilets ) (Green Pro certified make approved by bank or CPC team as exception/ Refer make and model sheet, vitrified floor tiles) Somany : Delmon Beige - (600 x 600) | E57: 102 | F57: 1359.32 | G57: 138650.64 | H57: 60.81 | I57: Sq.ft
A58: iv | B58: PAINTING WORKS | C58: PAINTING WORKS | D58: Similar as 9_a_iii but for providing and fixing 75mm high skirting/border. | E58: 57 | F58: 129.89 | G58: 7403.73 | H58: 3.25 | I58: R.ft
A59: b | B59: PAINTING WORKS | C59: PAINTING WORKS | D59: Ceramic Tile Flooring | E59: 0 | F59: 0 | G59: 0 | H59: 0
A60: i | B60: PAINTING WORKS | C60: PAINTING WORKS | D60: Proving and Laying of 300 mm x 300mm Ceramic floor tiles (use Green Pro certified make approved by bank or CPC team as exception/ Refer make and model sheet,ceramic tiles) (1st quality) of approved make over a 75 mm thk cement mortar (use Green Pro certified make approved by bank or CPC team as exception/ Refer make and model sheet,cement section) bedding (1: 4) as per the pattern given including colour cement joints in matching shade. Rate to include curing, acid wash, etc. complete. The joints shall be kept as thin as possible not exceeding 1 mm. (Basic cost of tile Rs. 35/- Sq. ft) | E60: 76 | F60: 0 | G60: 0 | H60: 0 | I60: Sq.ft
A61: ii | B61: POP Punning | C61: POP & FALSE CEILING WORKS | D61: Similar to above but for providing and fixing 3" high skirting/border. | E61: 38 | F61: 0 | G61: 0 | H61: 0 | I61: R.ft
A62: c | B62: POP Punning | C62: POP & FALSE CEILING WORKS | D62: Granite Flooring | E62: 0 | F62: 0 | G62: 0 | H62: 0
A63: i | B63: POP Punning | C63: POP & FALSE CEILING WORKS | D63: Supplying and laying 12 mm thk machine cut & machine polished Granite flooring , on a prefinished surface with 1:3 cement sand mortar (Green Pro certified make approved by bank or CPC team as exception/ Refer make and model sheet,cement section) .(Basic cost of granite Rs 180 /sq.ft). Rate shall be inclusive of machine polishing edges in case of protruding edges & groove if ordered. . Measurement for payment shall be as per laid area . | E63: 317 | F63: 0 | G63: 0 | H63: 0 | I63: Sq.ft
A64: ii | B64: POP Punning | C64: POP & FALSE CEILING WORKS | D64: Similar to above but 75mm high skirting/border. | E64: 128 | F64: 0 | G64: 0 | H64: 0 | I64: R.ft
A65: d | B65: POP Punning | C65: POP & FALSE CEILING WORKS | D65: Vitrified Tiles in wooden finish (in HNW areas with prior approval) | E65: 0 | F65: 0 | G65: 0 | H65: 0
A66: i | B66: POP Punning | C66: POP & FALSE CEILING WORKS | D66: Same as item 9.a-(i) but vitrified tiles in wooden finish. (Green Pro certified make approved by bank or CPC team as exception/ Refer make and model sheet,vitrified floor tiles) (Basic cost of tile Rs.85/- per sq ft.) | E66: 122 | F66: 0 | G66: 0 | H66: 0 | I66: Sq.ft
A67: e | B67: POP Punning | C67: POP & FALSE CEILING WORKS | D67: Carpet Flooring (in HNW areas with prior approval) | E67: 0 | F67: 0 | G67: 0 | H67: 0
A68: i | B68: POP Punning | C68: POP & FALSE CEILING WORKS | D68: Providing and laying carpet of 20 ounce loop pile in polypropylene in carpet tile (Green Pro certified make approved by bank or CPC team as exception/ Refer make and model sheet,vitrified floor tiles)form without underlay. Cost also included surface preparation required for laying of it and carpet protection. ( Basic cost of tile Rs.160 /- per sq ft.) | E68: 152 | F68: 0 | G68: 0 | H68: 0 | I68: Sq.ft
A69: f | B69: POP Punning | C69: POP & FALSE CEILING WORKS | D69: Vinyl Flooring | E69: 0 | F69: 0 | G69: 0 | H69: 0
A70: i | B70: POP Punning | C70: POP & FALSE CEILING WORKS | D70: Providing fixing Vinyl Anti-Static flooring 5 mm thick Armstrong/LG/Tusker installed on smooth, hard & absolutely levelled sub-floor. Brushed SS edges shall be used at the seams. Conductive adhesives shall be used for fixing . | E70: 105 | F70: 418.52 | G70: 43944.6 | H70: 19.27 | I70: Sq.ft
A71: g | B71: POP Punning | C71: POP & FALSE CEILING WORKS | D71: False Flooring | E71: 0 | F71: 0 | G71: 0 | H71: 0
A72: i | B72: POP Punning | C72: POP & FALSE CEILING WORKS | D72: P/F Raised access floor (false floor app. 150 mm to 230 mm high) .The panel shall be finished with antistatic 600x600x1.5mm laminate laid on base panels with solvent free epoxy, edge shall have 0.6mm PVC lipping & floor shall have UDL of 10 KN/Sq.m point load of 2.5 | E72: 339 | F72: 73.32 | G72: 24855.48 | H72: 10.9 | I72: Sq.ft
A73: ii | B73: POP Punning | C73: POP & FALSE CEILING WORKS | D73: P/F Raised access floor (false floor app. 300 mm high) .The panel shall be finished with antistatic 600x600x1.5mm laminate laid on base panels with solvent free epoxy, edge shall have 0.6mm PVC lipping & floor shall have UDL of 10 KN/Sq.m point load of 2.5 | E73: 350 | F73: 0 | G73: 0 | H73: 0 | I73: Sq.ft
A74: h | B74: POP Punning | C74: POP & FALSE CEILING WORKS | D74: POP covering on Flooring | E74: 0 | F74: 0 | G74: 0 | H74: 0
A75: i | B75: POP Punning | C75: POP & FALSE CEILING WORKS | D75: Providing and applying POP covering on flooring for floor protection with plastic sheet between the flooring and POP. The rate should include the cleaning of POP and plastic on completion before handing over completed site. | E75: 12 | F75: 0 | G75: 0 | H75: 0 | I75: Sq.ft
A76: ii | B76: POP Punning | C76: POP & FALSE CEILING WORKS | D76: Providing and applying covering on flooring for floor protection with Heavy duty bubble sheet on newly placed flooring. The rate should include the cleaning of plastic on completion before handing over completed site. | E76: 12 | F76: 2049.09 | G76: 24589.08 | H76: 10.78 | I76: Sq.ft
A77: i | B77: POP Punning | C77: POP & FALSE CEILING WORKS | D77: Wall Dado Tiles | E77: 0 | F77: 0 | G77: 0 | H77: 0
A78: i | B78: POP Punning | C78: POP & FALSE CEILING WORKS | D78: Proving and Laying Ceramic glaze Wall Tiles (Green Pro certified make approved by bank or CPC team as exception/ Refer make and model sheet,cement section) ( Colour : White ) of size 450mm x 300mm (1st quality) of somany make or approved make over a cement mortar bedding (1:4) (use Green Pro certified make approved by bank or CPC team as exception/ Refer make and model sheet,cement section) as per the pattern given including filling joint with colour cement in matching shade. (Basic cost of tiles Rs. 50/- Sq.ft). | E78: 76 | F78: 0 | G78: 0 | H78: 0 | I78: Sq.ft
A79: ii | B79: POP Punning | C79: POP & FALSE CEILING WORKS | D79: Proving and Laying wall dado Vitrified glaze tiles of size 600 mm X 600 mm (1st quality) of approved make over a cement mortar (Green Pro certified make approved by bank or CPC team as exception/ Refer make and model sheet,cement section) bedding (1:4) as per the pattern given including filling joint with colour cement in matching shade. (Basic cost of tiles upto Rs. 65/- Sq.ft). (Green Pro certified make approved by bank or CPC team as exception/ Refer make and model sheet, wall tiles) Somany : Delmon Beige - (600 x 600) | E79: 99 | F79: 0 | G79: 0 | H79: 0 | I79: Sq.ft
A80: 10 | B80: POP Punning | C80: POP & FALSE CEILING WORKS | D80: Pantry / Dining / Toilet Counter & Thresholds | E80: 0 | F80: 0 | G80: 0 | H80: 0
A81: a | B81: POP Punning | C81: POP & FALSE CEILING WORKS | D81: Providing & fixing 600mm deep pantry counter made out of 12mm thk black granite supported by 25mm thk Kadappa to be fixed horizontally and vertically. The cost to be included of the platform to have 75mm wide granite fascia horizontally with molded edges as per design. 100mm high granite band over dado level to be provided. 75mm thk platform at floor level inside the counter should be provided finished with 75mm high granite skirting from outside The cost to include of making hole in the counter for fixing sink, End verticals to be fixed made of Kadappa and covered with granite to be provided as per the design. (Basic Cost of Granite 180/- sq.ft). Cost of Storage, CP fittings, SS sink are not included. | E81: 2796 | F81: 20 | G81: 55920 | H81: 24.53 | I81: R.ft
A82: b | B82: POP Punning | C82: POP & FALSE CEILING WORKS | D82: Providing & Fixing Dining Counter with S.S Angle Bracket in approved Black Granite finish at ht. 750 mm from Finished Floor Level.(Depth of Counter 600 mm) (Basic Cost of Granite 180/- sq.ft) | E82: 1483 | F82: 0 | G82: 0 | H82: 0 | I82: R.ft
A83: c | B83: POP Punning | C83: POP & FALSE CEILING WORKS | D83: Providing & fixing wash basin counter in Toilets of 600 mm Deep made of 12 mm thk black granite supported on 25thk Kadappa base. 75 mm wide granite facia to be provided at the edge of the counter. The cost to include of making hole in the counter for fixing wash basin, Cost of CP fittings, Wash basin are not included. (Basic Cost of Granite 180/- sq.ft) | E83: 1815 | F83: 0 | G83: 0 | H83: 0 | I83: R.ft
A84: d | B84: POP Punning | C84: POP & FALSE CEILING WORKS | D84: Providing & Fixing of size 450mm X 900mm both sides polished divider for Urinal made of 12mm thk Black Granite embedded in the wall. The edges of the granite to be machine polished. | E84: 1716 | F84: 1 | G84: 1716 | H84: 0.75 | I84: Nos.
A85: e | B85: POP Punning | C85: POP & FALSE CEILING WORKS | D85: Providing & Laying 150mm wide Black Granite Threshold at ATM and Main Entrance. (Basic Cost of Granite 180/- sq.ft) | E85: 211 | F85: 29.41 | G85: 6205.51 | H85: 2.72 | I85: R.ft
A86: f | B86: POP Punning | C86: POP & FALSE CEILING WORKS | D86: Providing & Laying 75 mm wide Black Granite Threshold for Toilets & Pantry. (Basic Cost of Granite 180/- sq.ft) | E86: 177 | F86: 11.5 | G86: 2035.5 | H86: 0.89 | I86: R.ft
A87: 11 | B87: POP Punning | C87: POP & FALSE CEILING WORKS | D87: External Paving/Flooring/Window sill | E87: 0 | F87: 0 | G87: 0 | H87: 0
A88: a | B88: POP Punning | C88: POP & FALSE CEILING WORKS | D88: Supplying and laying 20 mm thk glossy chequered tiles heavy duty external grade for paving on a prefinished surface with 1:3 cement (use Green Pro certified make approved by bank or CPC team as exception/ Refer make and model sheet,cement section) sand mortar over a 50 mm thk cement mortar bedding (1: 4) / PCC as per the design including colour cement float joints in matching shade. (Basic cost of tiles Rs.35 /- per sq. ft.) | E88: 91 | F88: 0 | G88: 0 | H88: 0 | I88: Sq.ft
A89: b | B89: POP Punning | C89: POP & FALSE CEILING WORKS | D89: Providing and laying inter locking Paver blocks (heavy duty) in two or more shades by excavating the existing surface by @ 150mm to 230mm and providing layer for gravel over the entire area and covering the same with a layer of graded sand limestone, screeding / sinner to the required slope and providing primer locking pave blocks. The rate is inclusive of PCC (1:2:4) bed at the edges of the pattern as per site conditions. (Basic cost of tiles Rs.40 /- per sq. ft.) | E89: 98 | F89: 0 | G89: 0 | H89: 0 | I89: Sq.ft
A90: c | B90: POP Punning | C90: POP & FALSE CEILING WORKS | D90: Providing and laying Kotah stone, flooring 25mm-30mm thk. Having sizes not less than 55cms x 55 cms in plain/ diamond pattern and bed of 1:6 cm including cement float filling joints with neat cement slurry, curing, polishing and clearing complete in all respect. (for strong room flooring) | E90: 110 | F90: 0 | G90: 0 | H90: 0 | I90: Sq.ft
A91: d | B91: POP Punning | C91: POP & FALSE CEILING WORKS | D91: Treads & risers of steps. Providing and laying in required position polished granite slab 18mm thk with machine cut and machine polish in CM 1:3 for treads/ risers of steps. The rate is inclusive of full rounded nosing for treads and 3 no's groove on treads complete in all respect. ' The granite to be fixed with adhesive (approved Low VOC/No VOC Adhesives to be used by Bank or CPC team as exception / Refer Make and Model sheet, Adhesives) in case the same is to be fixed on a plywood surface. (Basic cost of Jet black granite Rs. 180/- sq.ft.) | E91: 314 | F91: 0 | G91: 0 | H91: 0 | I91: Sq.ft
A92: e | B92: POP Punning | C92: POP & FALSE CEILING WORKS | D92: Sill & jambs to windows / Doors. Providing and laying in required positions granite, slab 12 mm thk (Single piece), of approved make & colour with machine, cut and machine polish up to 145mm wide ; in cement mortar (Green Pro certified make approved by bank or CPC team as exception/ Refer make and model sheet,cement section) of 1:3 for sills and jambs of windows .The rate is inclusive of full rounded molding at the edges from inside. (Basic cost of granite Rs. 180/- sq.ft.) | E92: 194 | F92: 85.04 | G92: 16497.76 | H92: 7.24 | I92: R.ft
A93: f | B93: POP Punning | C93: POP & FALSE CEILING WORKS | D93: Providing and laying jambs to door at required positions granite slab 12mm thk. Up to 2100mm in length (Double piece) and machine polish up to 145mm wide ; in cement mortar (Green Pro certified make approved by bank or CPC team as exception/ Refer make and model sheet,cement section) of 1:3 for jambs of door .The rate is inclusive of fillet rounded molding at the edges from inside. (Basic cost of granite Rs. 180/- sq.ft.) | E93: 385 | F93: 84 | G93: 32340 | H93: 14.18 | I93: R.ft
A94: g | B94: POP Punning | C94: POP & FALSE CEILING WORKS | D94: Treads & risers of steps. Providing and laying in required position granite slab 12mm thk with machine cut and machine polish in 19 mm BWP Plywood (BWP Plywood which are "Free of Added Urea Formaldehyde" (required) approved by Bank or CPC team as exception / Refer Make and Model sheet, BWP Plywood) for treads/ risers of steps of internal staircase of branch. The rate is inclusive of full rounded nosing for treads and 3 no's groove on treads complete in all respect. ' The granite to be fixed with adhesive (approved Low VOC/No VOC Adhesives to be used by Bank or CPC team as exception / Refer Make and Model sheet, Adhesives) in case the same is to be fixed on a plywood surface. (Basic cost of granite Rs. 180/- sq.ft.) | E94: 396 | F94: 0 | G94: 0 | H94: 0 | I94: Sq.ft
A95: 12 | B95: POP Punning | C95: POP & FALSE CEILING WORKS | D95: Façade Treatment | E95: 0 | F95: 0 | G95: 0 | H95: 0
A96: a | B96: POP Punning | C96: POP & FALSE CEILING WORKS | D96: P/F 12mm thk Black Granite to be fixed with approved adhesive (approved Low VOC/No VOC Adhesives to be used by Bank or CPC team as exception / Refer Make and Model sheet, Adhesives) and curing on plywood base (use Plywood which are "Free of Added Urea Formaldehyde" (required) and Green Pro certified (Mandatory) and make approved by Bank or CPC team as exception / Refer Make and Model sheet, BWR Plywood) paneling on the façade. (Cost of plywood paneling not included). (Basic cost of granite Rs. 180/- sq.ft.) | E96: 474 | F96: 0 | G96: 0 | H96: 0 | I96: Sq.ft
A97: 13 | B97: POP Punning | C97: POP & FALSE CEILING WORKS | D97: Handicapped Access Ramp | E97: 0 | F97: 0 | G97: 0 | H97: 0
A98: a | B98: POP Punning | C98: POP & FALSE CEILING WORKS | D98: Providing and constructing handicapped ramp at a slope of 1:12 or as per site conditions with raised floor to be made by filling dubber stone soling and compacted by sand dust & 1:4 cement mortar ( Green Pro certified make approved by bank or CPC team as exception/ Refer make and model sheet, cement) to match the required level. The width of ramp should be minimum upto 1200mm | E98: 1114 | F98: 0 | G98: 0 | H98: 0 | I98: R.ft
A99: b | B99: POP Punning | C99: POP & FALSE CEILING WORKS | D99: Providing and constructing raised floor for staircase and midlanding by filling dubber stone soling and compacted by sand dust ,1:4 cement mortar (use Green Pro certified make approved by bank or CPC team as exception/ Refer make and model sheet,cement section) to match the required level. | E99: 271 | F99: 0 | G99: 0 | H99: 0 | I99: Sq.ft
A100: 14 | B100: POP Punning | C100: POP & FALSE CEILING WORKS | D100: Ramp Finishes | E100: 0 | F100: 0 | G100: 0 | H100: 0
...

Sheet Summary Sheet
A1: Sr. No | B1: Particulars | C1: Amount As per CWI | D1: Rate per sq.feet
A2: I | B2: POP & FALSE CEILING WORKS | C2: 1733162.6 | D2: 760
A3: II | B3: CARPENTRY AND INTERIOR WORKS | C3: 763801.48 | D3: 335
A4: III | B4: PAINTING WORKS | C4: 95319.01 | D4: 42
A5: IV | B5: ROLLING SHUTTER AND MS WORK | C5: 442709.8 | D5: 194
A6: V | B6: ELECTRIFICATION AND ALLIED WORKS | C6: 1576638.6 | D6: 692
A7: VI | B7: Additional Work | C7: 162810.6 | D7: 71
A8: Total | B8: Total | C8: 4774442.1 | D8: 2094

Sheet BOQ
C1: As per Work Order | G1: As per CWI | J1: Variance: CWI vs WO | L1: Excess | M1: Savings | N1: Total | O1: Remarks
A2: Sr. No | B2: Particulars | C2: Qty | D2: Unit | E2: Rate | F2: Amount | G2: Qty | H2: Round off | I2: Amount | J2: Qty. | K2: Amount | L2: Amount | M2: Amount | N2: Amount | O2: Remarks
A3: I | B3: CIVIL & RELATED WORKS
A4: 1 | B4: Demolition / Clearing Works
A5: a | B5: Dismantling/Demolishing the following and carting away the debris from the site and unloading at a approved location as per statutory rules and regulations.
A6: i | B6: Dismantling of existing brickwork | D6: Sq.ft | E6: 12 | F6: =E6*C6 -> 0 | H6: =ROUND(G6,2) -> 0 | I6: =H6*E6 -> 0 | J6: =G6-C6 -> 0 | K6: =I6-F6 -> 0 | L6: =IF(F6<I6,(I6-F6),0) -> 0 | M6: =IF(F6>I6,(I6-F6),0) -> 0 | N6: =M6+L6 -> 0
A7: ii | B7: Dismantling of existing dado tiles without plaster | D7: Sq.ft | E7: 11 | F7: =E7*C7 -> 0 | G7: ='Measurement sheet'!F26 -> 932.39 | H7: =ROUND(G7,2) -> 932.39 | I7: =H7*E7 -> 10256.29 | J7: =G7-C7 -> 932.39 | K7: =I7-F7 -> 10256.29 | L7: =IF(F7<I7,(I7-F7),0) -> 10256.29 | M7: =IF(F7>I7,(I7-F7),0) -> 0 | N7: =M7+L7 -> 10256.29 | O7: Quantity measured on best effort basis from photographs and layouts. PM confirmation required for whether items were executed on site and Qty not Present in WO.
A8: iii | B8: Dismantling of existing plaster | D8: Sq.ft | E8: 11 | F8: =E8*C8 -> 0 | G8: ='Measurement sheet'!F35 -> 459.7317 | H8: =ROUND(G8,2) -> 459.73 | I8: =H8*E8 -> 5057.03 | J8: =G8-C8 -> 459.7317 | K8: =I8-F8 -> 5057.03 | L8: =IF(F8<I8,(I8-F8),0) -> 5057.03 | M8: =IF(F8>I8,(I8-F8),0) -> 0 | N8: =M8+L8 -> 5057.03 | O8: Quantity measured on best effort basis from photographs and layouts. PM confirmation required for whether items were executed on site and Qty not Present in WO.
A9: iv | B9: Existing flooring including bedding material & PCC/IPS. | D9: Sq.ft | E9: 16 | F9: =E9*C9 -> 0 | G9: ='Measurement sheet'!F47 -> 540.8335 | H9: =ROUND(G9,2) -> 540.83 | I9: =H9*E9 -> 8653.28 | J9: =G9-C9 -> 540.8335 | K9: =I9-F9 -> 8653.28 | L9: =IF(F9<I9,(I9-F9),0) -> 8653.28 | M9: =IF(F9>I9,(I9-F9),0) -> 0 | N9: =M9+L9 -> 8653.28 | O9: Quantity measured on best effort basis from photographs and layouts. PM confirmation required for whether items were executed on site and Qty not Present in WO.
A10: v | B10: Existing Doors / Windows | D10: Nos. | E10: 381 | F10: =E10*C10 -> 0 | G10: ='Measurement sheet'!F51 -> 16 | H10: =ROUND(G10,2) -> 16 | I10: =H10*E10 -> 6096 | J10: =G10-C10 -> 16 | K10: =I10-F10 -> 6096 | L10: =IF(F10<I10,(I10-F10),0) -> 6096 | M10: =IF(F10>I10,(I10-F10),0) -> 0 | N10: =M10+L10 -> 6096 | O10: Quantity measured on best effort basis from photographs and layouts. PM confirmation required for whether items were executed on site and Qty not Present in WO.
A11: vi | B11: Dismantling of existing Sanitary wares & Plumbing Fittings | D11: Nos. | E11: 1199 | F11: =E11*C11 -> 0 | H11: =ROUND(G11,2) -> 0 | I11: =H11*E11 -> 0 | J11: =G11-C11 -> 0 | K11: =I11-F11 -> 0 | L11: =IF(F11<I11,(I11-F11),0) -> 0 | M11: =IF(F11>I11,(I11-F11),0) -> 0 | N11: =M11+L11 -> 0
A12: vii | B12: Existing Rolling Shutter , Safety door, collapsible door etc. | D12: Sq.ft | E12: 11 | F12: =E12*C12 -> 0 | H12: =ROUND(G12,2) -> 0 | I12: =H12*E12 -> 0 | J12: =G12-C12 -> 0 | K12: =I12-F12 -> 0 | L12: =IF(F12<I12,(I12-F12),0) -> 0 | M12: =IF(F12>I12,(I12-F12),0) -> 0 | N12: =M12+L12 -> 0
A13: viii | B13: Existing Electrical fittings and fixtures | D13: Sq.ft | E13: 3 | F13: =E13*C13 -> 0 | H13: =ROUND(G13,2) -> 0 | I13: =H13*E13 -> 0 | J13: =G13-C13 -> 0 | K13: =I13-F13 -> 0 | L13: =IF(F13<I13,(I13-F13),0) -> 0 | M13: =IF(F13>I13,(I13-F13),0) -> 0 | N13: =M13+L13 -> 0
A14: ix | B14: Dismantling of existing wooden & aluminum partitions | D14: Sq.ft | E14: 10 | F14: =E14*C14 -> 0 | H14: =ROUND(G14,2) -> 0 | I14: =H14*E14 -> 0 | J14: =G14-C14 -> 0 | K14: =I14-F14 -> 0 | L14: =IF(F14<I14,(I14-F14),0) -> 0 | M14: =IF(F14>I14,(I14-F14),0) -> 0 | N14: =M14+L14 -> 0
A15: x | B15: Miscellaneous items such as false ceilings. | D15: Sq.ft | E15: 11 | F15: =E15*C15 -> 0 | H15: =ROUND(G15,2) -> 0 | I15: =H15*E15 -> 0 | J15: =G15-C15 -> 0 | K15: =I15-F15 -> 0 | L15: =IF(F15<I15,(I15-F15),0) -> 0 | M15: =IF(F15>I15,(I15-F15),0) -> 0 | N15: =M15+L15 -> 0
A16: xi | B16: Shifting /Dismantling existing furniture items (For renovation projects only) | D16: Nos. | E16: 487 | F16: =E16*C16 -> 0 | H16: =ROUND(G16,2) -> 0 | I16: =H16*E16 -> 0 | J16: =G16-C16 -> 0 | K16: =I16-F16 -> 0 | L16: =IF(F16<I16,(I16-F16),0) -> 0 | M16: =IF(F16>I16,(I16-F16),0) -> 0 | N16: =M16+L16 -> 0
A17: xii | B17: Dismantling of existing RCC 6 "/ 9" thk wall. | D17: Sq.ft | E17: 84 | F17: =E17*C17 -> 0 | G17: ='Measurement sheet'!F54 -> 2 | H17: =ROUND(G17,2) -> 2 | I17: =H17*E17 -> 168 | J17: =G17-C17 -> 2 | K17: =I17-F17 -> 168 | L17: =IF(F17<I17,(I17-F17),0) -> 168 | M17: =IF(F17>I17,(I17-F17),0) -> 0 | N17: =M17+L17 -> 168 | O17: Quantity measured on best effort basis from photographs and layouts. PM confirmation required for whether items were executed on site and Qty not Present in WO.
A19: 2 | B19: Construction of Masonry Walls
A20: a | B20: Providing and erecting 115 mm thk , Half brick wall (first class bricks) in cement and sand mortar 1:3 with flush joint complete with material, labour, scaffolding, curing etc. The rate to include Appling chicken mesh at RCC to brickwork joints wherever required and RCC stiffener at every 1 meter intervals in 1:2:4 concrete. (Excluding plastering). The work to include cost for lintels / sills in RCC required for Doors , windows, openings etc. | D20: Sq.ft | E20: 114 | F20: =E20*C20 -> 0 | H20: =ROUND(G20,2) -> 0 | I20: =H20*E20 -> 0 | J20: =G20-C20 -> 0 | K20: =I20-F20 -> 0 | L20: =IF(F20<I20,(I20-F20),0) -> 0 | M20: =IF(F20>I20,(I20-F20),0) -> 0 | N20: =M20+L20 -> 0
A21: b | B21: Same as 2(a) but 230mm thk ( Single brick wall) | D21: Sq.ft | E21: 150 | F21: =E21*C21 -> 0 | H21: =ROUND(G21,2) -> 0 | I21: =H21*E21 -> 0 | J21: =G21-C21 -> 0 | K21: =I21-F21 -> 0 | L21: =IF(F21<I21,(I21-F21),0) -> 0 | M21: =IF(F21>I21,(I21-F21),0) -> 0 | N21: =M21+L21 -> 0
A22: c | B22: Do-do as 2(a) above but 100mm thk siporex / AAC / Aerocon / light weight block wall (Green Pro certified make approved by bank or CPC team as exception/ Refer make and model sheet,aerocon blocks) | D22: Sq.ft | E22: 124 | F22: =E22*C22 -> 0 | H22: =ROUND(G22,2) -> 0 | I22: =H22*E22 -> 0 | J22: =G22-C22 -> 0 | K22: =I22-F22 -> 0 | L22: =IF(F22<I22,(I22-F22),0) -> 0 | M22: =IF(F22>I22,(I22-F22),0) -> 0 | N22: =M22+L22 -> 0
A23: d | B23: Do-do as 2(a) above but 150mm thk siporex / AAC / Aerocon / light weight block wall (Green Pro certified make approved by bank or CPC team as exception/ Refer make and model sheet,aerocon blocks) | C23: 850 | D23: Sq.ft | E23: 129 | F23: =E23*C23 -> 109650 | G23: ='Measurement sheet'!F80 -> 851.395 | H23: =ROUND(G23,2) -> 851.4 | I23: =H23*E23 -> 109830.6 | J23: =G23-C23 -> 1.395 | K23: =I23-F23 -> 180.6 | L23: =IF(F23<I23,(I23-F23),0) -> 180.6 | M23: =IF(F23>I23,(I23-F23),0) -> 0 | N23: =M23+L23 -> 180.6 | O23: Quantiy has exceeded WO Quantity, PM Approval is required for excess quantity
A25: 3 | B25: R.C.C Works
A26: a | B26: R.C.C work :Providing & casting in-situ reinforced cement concrete 225 mm thick for wall/columns/ as per details/ drawings/ design( The rate to include cost of re-baring/Hilti/drilling and joining with existing beam or lintel including shuttering, steel , concrete, inserts, cutout for ventilator, hacking, curing, bonding chemical / slurry all complete, design and certification from structural consultant. Grade of concrete to be considered shall be M25 & steel to be considered as 12mm dia tor steel @150mm c/c both way in two layers staggered by 75mm in both directions. The thickness of walls to be 225 mm without plaster. 300mm x300mm RCC column to be provided near the strong room door for mounting strong room door. | D26: Sq.ft | E26: 444 | F26: =E26*C26 -> 0 | H26: =ROUND(G26,2) -> 0 | I26: =H26*E26 -> 0 | J26: =G26-C26 -> 0 | K26: =I26-F26 -> 0 | L26: =IF(F26<I26,(I26-F26),0) -> 0 | M26: =IF(F26>I26,(I26-F26),0) -> 0 | N26: =M26+L26 -> 0
A27: b | B27: Do-do as 3(a) above but Ready mix concrete (Green Pro certified make approved by bank or CPC team as exception/ Refer make and model sheet,RMC) | D27: Sq.ft | E27: 699 | F27: =E27*C27 -> 0 | H27: =ROUND(G27,2) -> 0 | I27: =H27*E27 -> 0 | J27: =G27-C27 -> 0 | K27: =I27-F27 -> 0 | L27: =IF(F27<I27,(I27-F27),0) -> 0 | M27: =IF(F27>I27,(I27-F27),0) -> 0 | N27: =M27+L27 -> 0
A28: c | B28: Similar to above but for Floor slab with single layer of steel comprising 12mm dia @150 mm c/c and concrete jointing compound to be provided in case the premises is located on first floor and floor below does not belong to the bank. | D28: Sq.ft | E28: 198 | F28: =E28*C28 -> 0 | H28: =ROUND(G28,2) -> 0 | I28: =H28*E28 -> 0 | J28: =G28-C28 -> 0 | K28: =I28-F28 -> 0 | L28: =IF(F28<I28,(I28-F28),0) -> 0 | M28: =IF(F28>I28,(I28-F28),0) -> 0 | N28: =M28+L28 -> 0
A29: d | B29: Do-do as 3(c) above but Ready mix concrete (Green Pro certified make approved by bank or CPC team as exception/ Refer make and model sheet,RMC) | D29: Sq.ft | E29: 330 | F29: =E29*C29 -> 0 | H29: =ROUND(G29,2) -> 0 | I29: =H29*E29 -> 0 | J29: =G29-C29 -> 0 | K29: =I29-F29 -> 0 | L29: =IF(F29<I29,(I29-F29),0) -> 0 | M29: =IF(F29>I29,(I29-F29),0) -> 0 | N29: =M29+L29 -> 0
A30: e | B30: Similar to above but for Floor slab with double layer of steel comprising of 12 mm dia @ 150 mm c/c Mesh on both ways staggered by 75mm and concrete jointing compound to be provided in case the premises is located on first floor and floor below does not belong to the bank. | D30: Sq.ft | E30: 336 | F30: =E30*C30 -> 0 | H30: =ROUND(G30,2) -> 0 | I30: =H30*E30 -> 0 | J30: =G30-C30 -> 0 | K30: =I30-F30 -> 0 | L30: =IF(F30<I30,(I30-F30),0) -> 0 | M30: =IF(F30>I30,(I30-F30),0) -> 0 | N30: =M30+L30 -> 0
A31: f | B31: Do-do as 3(f) above but Ready mix concrete (Green Pro certified make approved by bank or CPC team as exception/ Refer make and model sheet,RMC) | D31: Sq.ft | E31: 453 | F31: =E31*C31 -> 0 | H31: =ROUND(G31,2) -> 0 | I31: =H31*E31 -> 0 | J31: =G31-C31 -> 0 | K31: =I31-F31 -> 0 | L31: =IF(F31<I31,(I31-F31),0) -> 0 | M31: =IF(F31>I31,(I31-F31),0) -> 0 | N31: =M31+L31 -> 0
A32: g | B32: Similar to above but without concrete (ceiling reinforcement Mesh to be provided in case upper floor does not belong to the bank) | D32: Sq.ft | E32: 129 | F32: =E32*C32 -> 0 | H32: =ROUND(G32,2) -> 0 | I32: =H32*E32 -> 0 | J32: =G32-C32 -> 0 | K32: =I32-F32 -> 0 | L32: =IF(F32<I32,(I32-F32),0) -> 0 | M32: =IF(F32>I32,(I32-F32),0) -> 0 | N32: =M32+L32 -> 0
A33: i | B33: Do-do as 3(g) above but Ready mix concrete (Green Pro certified make approved by bank or CPC team as exception/ Refer make and model sheet,RMC) | D33: Sq.ft | E33: 389 | F33: =E33*C33 -> 0 | H33: =ROUND(G33,2) -> 0 | I33: =H33*E33 -> 0 | J33: =G33-C33 -> 0 | K33: =I33-F33 -> 0 | L33: =IF(F33<I33,(I33-F33),0) -> 0 | M33: =IF(F33>I33,(I33-F33),0) -> 0 | N33: =M33+L33 -> 0
A34: j | B34: Similar to item 3(c) i.e. 6mm MS plate instead of reinforcement mesh for wall cladding. Including necessary MS framework. Complete as directed. | D34: Sq.ft | E34: 468 | F34: =E34*C34 -> 0 | H34: =ROUND(G34,2) -> 0 | I34: =H34*E34 -> 0 | J34: =G34-C34 -> 0 | K34: =I34-F34 -> 0 | L34: =IF(F34<I34,(I34-F34),0) -> 0 | M34: =IF(F34>I34,(I34-F34),0) -> 0 | N34: =M34+L34 -> 0
A35: k | B35: Fixing in place of Strong Room Door by providing necessary grouting in the floor and proper support. The vendor should ensure that the door is fixed in plumb. | D35: Job | E35: 8559 | F35: =E35*C35 -> 0 | H35: =ROUND(G35,2) -> 0 | I35: =H35*E35 -> 0 | J35: =G35-C35 -> 0 | K35: =I35-F35 -> 0 | L35: =IF(F35<I35,(I35-F35),0) -> 0 | M35: =IF(F35>I35,(I35-F35),0) -> 0 | N35: =M35+L35 -> 0
A36: l | B36: Fixing in place of Ventilator by providing necessary grouting in the floor and proper support. The vendor should ensure that the door is fixed in plumb. | D36: Job | E36: 5720 | F36: =E36*C36 -> 0 | H36: =ROUND(G36,2) -> 0 | I36: =H36*E36 -> 0 | J36: =G36-C36 -> 0 | K36: =I36-F36 -> 0 | L36: =IF(F36<I36,(I36-F36),0) -> 0 | M36: =IF(F36>I36,(I36-F36),0) -> 0 | N36: =M36+L36 -> 0
A38: 4 | B38: Plaster
A39: a | B39: P/A 1:4 cement plaster(Green Pro certified make approved by bank or CPC team as exception/ Refer make and model sheet,cement) with waterproofing compound to brick/RCC work including scaffolding in single coat of minimum 12 mm thick finished to receive Plaster of Paris levelling coat. | C39: 2320 | D39: Sq.ft | E39: 46 | F39: =E39*C39 -> 106720 | G39: ='Measurement sheet'!F100 -> 2317.1297 | H39: =ROUND(G39,2) -> 2317.13 | I39: =H39*E39 -> 106587.98 | J39: =G39-C39 -> -2.8703 | K39: =I39-F39 -> -132.02 | L39: =IF(F39<I39,(I39-F39),0) -> 0 | M39: =IF(F39>I39,(I39-F39),0) -> -132.02 | N39: =M39+L39 -> -132.02
A40: b | B40: External Plaster in 1:3 with waterproofing compound to brick/RCC work up to 25mm thk including cost of scaffolding up to 20'.( Prior approval of Bank required) (Green Pro certified make approved by bank or CPC team as exception/ Refer make and model sheet,cement) | D40: Sq.ft | E40: 62 | F40: =E40*C40 -> 0 | H40: =ROUND(G40,2) -> 0 | I40: =H40*E40 -> 0 | J40: =G40-C40 -> 0 | K40: =I40-F40 -> 0 | L40: =IF(F40<I40,(I40-F40),0) -> 0 | M40: =IF(F40>I40,(I40-F40),0) -> 0 | N40: =M40+L40 -> 0
A42: 5 | B42: Waterproofing treatment
A43: a | B43: Providing & appling water proofing treatement by Mixing and applying two coats of ready-to-use acrylic polymer based waterproofing component on modified cement base of approved make to a thickness of 2 mm over the bottom and sides of toilet and pantry slabs, including preparation of surface, finishing, curing etc. all complete at all levels as per manufacturer's specifications and as directed. | C43: 380 | D43: Sq.ft | E43: 45 | F43: =E43*C43 -> 17100 | G43: ='Measurement sheet'!F113 -> 285.0835 | H43: =ROUND(G43,2) -> 285.08 | I43: =H43*E43 -> 12828.6 | J43: =G43-C43 -> -94.9165 | K43: =I43-F43 -> -4271.4 | L43: =IF(F43<I43,(I43-F43),0) -> 0 | M43: =IF(F43>I43,(I43-F43),0) -> -4271.4 | N43: =M43+L43 -> -4271.4
A45: 6 | B45: Brick Bat Coba
A46: a | B46: Proving and Laying brick bat coba up to 150mm thk in 1:4 cement mortar incl. of necessary slope towards nahni trap, over waterproofing course including finishing the top surface with water proofing compound to receive the floor tiles as per India Waterproofing Co. Measurements of floor area shall only be considered for said works.(Toilet area) | C46: 140 | D46: Sq.ft | E46: 88 | F46: =E46*C46 -> 12320 | G46: ='Measurement sheet'!F121 -> 109.2835 | H46: =ROUND(G46,2) -> 109.28 | I46: =H46*E46 -> 9616.64 | J46: =G46-C46 -> -30.7165 | K46: =I46-F46 -> -2703.36 | L46: =IF(F46<I46,(I46-F46),0) -> 0 | M46: =IF(F46>I46,(I46-F46),0) -> -2703.36 | N46: =M46+L46 -> -2703.36
A48: 7 | B48: Plain Cement Concrete
A49: a | B49: P/E Plain cement concrete (Green Pro certified make approved by bank or CPC team as exception/ Refer make and model sheet,cement section) of grade M -10 ( 1:3:6 ) including shuttering for levelling course for flooring within the Bank Premise. The thickness may vary from 75mm to 125 mm as per requirement. (As per site condition - Prior approval of Bank required) | C49: 100 | D49: Sq.ft | E49: 50 | F49: =E49*C49 -> 5000 | G49: ='Measurement sheet'!F131 -> 534.5 | H49: =ROUND(G49,2) -> 534.5 | I49: =H49*E49 -> 26725 | J49: =G49-C49 -> 434.5 | K49: =I49-F49 -> 21725 | L49: =IF(F49<I49,(I49-F49),0) -> 21725 | M49: =IF(F49>I49,(I49-F49),0) -> 0 | N49: =M49+L49 -> 21725 | O49: Quantity measured on best effort basis from photographs and layouts. PM confirmation required for Quantiy has exceeded WO Quantity
A50: b | B50: Same as 7(A) but for depth upto 250 mm | D50: Sq.ft | E50: 105 | F50: =E50*C50 -> 0 | H50: =ROUND(G50,2) -> 0 | I50: =H50*E50 -> 0 | J50: =G50-C50 -> 0 | K50: =I50-F50 -> 0 | L50: =IF(F50<I50,(I50-F50),0) -> 0 | M50: =IF(F50>I50,(I50-F50),0) -> 0 | N50: =M50+L50 -> 0
A51: c | B51: Do-do as 7(a) above but Ready mix concrete (Green Pro certified make approved by bank or CPC team as exception/ Refer make and model sheet,RMC) | D51: Sq.ft | E51: 72 | F51: =E51*C51 -> 0 | H51: =ROUND(G51,2) -> 0 | I51: =H51*E51 -> 0 | J51: =G51-C51 -> 0 | K51: =I51-F51 -> 0 | L51: =IF(F51<I51,(I51-F51),0) -> 0 | M51: =IF(F51>I51,(I51-F51),0) -> 0 | N51: =M51+L51 -> 0
A52: d | B52: Do-do as 7(b) above but Ready mix concrete (Green Pro certified make approved by bank or CPC team as exception/ Refer make and model sheet,RMC) | D52: Sq.ft | E52: 139 | F52: =E52*C52 -> 0 | H52: =ROUND(G52,2) -> 0 | I52: =H52*E52 -> 0 | J52: =G52-C52 -> 0 | K52: =I52-F52 -> 0 | L52: =IF(F52<I52,(I52-F52),0) -> 0 | M52: =IF(F52>I52,(I52-F52),0) -> 0 | N52: =M52+L52 -> 0
A53: e | B53: Similar to above but for exterior works (As per site condition - Prior approval of Bank required) | D53: Sq.ft | E53: 64 | F53: =E53*C53 -> 0 | H53: =ROUND(G53,2) -> 0 | I53: =H53*E53 -> 0 | J53: =G53-C53 -> 0 | K53: =I53-F53 -> 0 | L53: =IF(F53<I53,(I53-F53),0) -> 0 | M53: =IF(F53>I53,(I53-F53),0) -> 0 | N53: =M53+L53 -> 0
A54: f | B54: Do-do as 7(e) above but Ready mix concrete (Green Pro certified make approved by bank or CPC team as exception/ Refer make and model sheet,RMC) | D54: Sq.ft | E54: 80 | F54: =E54*C54 -> 0 | H54: =ROUND(G54,2) -> 0 | I54: =H54*E54 -> 0 | J54: =G54-C54 -> 0 | K54: =I54-F54 -> 0 | L54: =IF(F54<I54,(I54-F54),0) -> 0 | M54: =IF(F54>I54,(I54-F54),0) -> 0 | N54: =M54+L54 -> 0
A55: g | B55: Providing and laying cement concrete flooring 40 - 50 mm thick , C.M. 1:3 laid to proper level and slope cost should including compaction as directed and curing complete in all respect. (As per site condition - Prior approval of Bank required)(Green Pro certified make approved by bank or CPC team as exception/ Refer make and model sheet,cement section) | D55: Sq.ft | E55: 38 | F55: =E55*C55 -> 0 | H55: =ROUND(G55,2) -> 0 | I55: =H55*E55 -> 0 | J55: =G55-C55 -> 0 | K55: =I55-F55 -> 0 | L55: =IF(F55<I55,(I55-F55),0) -> 0 | M55: =IF(F55>I55,(I55-F55),0) -> 0 | N55: =M55+L55 -> 0
A57: 8 | B57: Drywall Panel
A58: a | B58: Providing and fixing of Solid Dry Wall Panel 75mm thick of size 2400/2700/3000mm in length and 600mm width certified by Green Building council having a unique tongue and groove jointing system. The panels are made of two fibre reinforced cement sheets enclosing a light weight aerated concrete core composed of cement, fly ash and other binders. Density is 720~780kg/cum, panel has Axial load carrying capacity min 83 KN/m with 2.5 times factor safety as per test method of ASTM -E-72:98 . These panels need to meet Uniformly distributed load (Bending load 80 -95kg/sqm & modulus of rupture 40-58kg/sqcm) as per test method ASTM-E-72:98 & IS 2380 Part 4. Thermal Conductivity typical K value - 0.17 ~0.21 W/m K, having a fire rating of 120 minutes as per BS 476 part 20-22 and sound transmission coefficient 36~40 as per IS 9901 (part 1) 1981 The wall panels to be installed with G.I Floor Channel : 14 x 75 x 25 mm size of 1 mm thick at bottom and 38 X75X 38 mm size with 1mm thickness at top. Tongue and Groove joints will be joined with elastomeric cementitious highly polymerized jointing compound as per manufacturer’s recommendation. Non-woven Self-adhesive glass fiber / fiber mesh tape in sufficient width to be applied to reinforce the exposed skin of jointing system. Jointing compound to be applied on joint finally to make good . Rate by the vendor to include scaffolding, lifting charges and jointing material, wastages etc. as a complete item of work excluding finishing etc. The installation will be done as per specification, drawing and as directed by EIC/consultant. All work to be done by certified installer with proper supervision following WMS and as per instruction of Engineering in charge. (Ideal for Server room , Solid Partition, Store rooms ) Approved Brands : HIL Limited , Visaka (Vnext) , Everest Panel) (Green Pro certified make approved by bank or CPC team as exception/ Refer make and model sheet, Aerocon Panel) | D58: Sq.ft | E58: 160 | F58: =E58*C58 -> 0 | H58: =ROUND(G58,2) -> 0 | I58: =H58*E58 -> 0 | J58: =G58-C58 -> 0 | K58: =I58-F58 -> 0 | L58: =IF(F58<I58,(I58-F58),0) -> 0 | M58: =IF(F58>I58,(I58-F58),0) -> 0 | N58: =M58+L58 -> 0
A59: b | B59: Do-do as 8(a) above but 100mm thk (Green Pro certified make approved by bank or CPC team as exception/ Refer make and model sheet, Aerocon Panel) | D59: Sq.ft | E59: 254 | F59: =E59*C59 -> 0 | H59: =ROUND(G59,2) -> 0 | I59: =H59*E59 -> 0 | J59: =G59-C59 -> 0 | K59: =I59-F59 -> 0 | L59: =IF(F59<I59,(I59-F59),0) -> 0 | M59: =IF(F59>I59,(I59-F59),0) -> 0 | N59: =M59+L59 -> 0
A61: 9 | B61: Flooring
A62: a | B62: Vitrified Tile Flooring
A63: i | B63: Vitrified Tile Flooring - Proving and Laying 1000mm x 1000mm / 800mm X 800 mm Vitrified floor tiles (Green Pro certified make approved by bank or CPC team as exception/ Refer make and model sheet,vitrified floor tiles) over a 75 mm thk cement mortar (Green Pro certified make approved by bank or CPC team as exception/ Refer make and model sheet,cement section) bedding (1: 4) as per the design. The joints shall be kept up to 4 mm and filled with epoxy grouting of approved shade. (Basic cost of tile up to up to Rs. 110/-Sq. ft). | C63: 2040 | D63: Sq.ft | E63: 152 | F63: =E63*C63 -> 310080 | G63: ='Measurement sheet'!F145 -> 2009.7808 | H63: =ROUND(G63,2) -> 2009.78 | I63: =H63*E63 -> 305486.56 | J63: =G63-C63 -> -30.2192 | K63: =I63-F63 -> -4593.44 | L63: =IF(F63<I63,(I63-F63),0) -> 0 | M63: =IF(F63>I63,(I63-F63),0) -> -4593.44 | N63: =M63+L63 -> -4593.44
A64: ii | B64: Similar to above but for providing and fixing 75mm high skirting/border. | D64: R.ft | E64: 66 | F64: =E64*C64 -> 0 | G64: ='Measurement sheet'!F150 -> 86.45 | H64: =ROUND(G64,2) -> 86.45 | I64: =H64*E64 -> 5705.7 | J64: =G64-C64 -> 86.45 | K64: =I64-F64 -> 5705.7 | L64: =IF(F64<I64,(I64-F64),0) -> 5705.7 | M64: =IF(F64>I64,(I64-F64),0) -> 0 | N64: =M64+L64 -> 5705.7 | O64: Quantity executed on site and verified during audit but not present in work order
A65: iii | B65: Proving and Laying 600mm x 600mm anti-skid and Anti-dust Vitrified floor tiles for Toilet floors with a 75 mm thk cement mortar (Green Pro certified make approved by bank or CPC team as exception/ Refer make and model sheet,cement section) bedding (1: 4) as per the design including colour cement in joint to matching shade. The joints shall be kept as thin as possible should not exceeding 1 mm. (Basic cost of tile upto Rs. 60 /-Sq. ft). ( For server room, store, pantry, toilets ) (Green Pro certified make approved by bank or CPC team as exception/ Refer make and model sheet, vitrified floor tiles) Somany : Delmon Beige - (600 x 600) | C65: 1660 | D65: Sq.ft | E65: 102 | F65: =E65*C65 -> 169320 | G65: ='Measurement sheet'!F179 -> 1359.3185 | H65: =ROUND(G65,2) -> 1359.32 | I65: =H65*E65 -> 138650.64 | J65: =G65-C65 -> -300.6815 | K65: =I65-F65 -> -30669.36 | L65: =IF(F65<I65,(I65-F65),0) -> 0 | M65: =IF(F65>I65,(I65-F65),0) -> -30669.36 | N65: =M65+L65 -> -30669.36
A66: iv | B66: Similar as 9_a_iii but for providing and fixing 75mm high skirting/border. | C66: 100 | D66: R.ft | E66: 57 | F66: =E66*C66 -> 5700 | G66: ='Measurement sheet'!F186 -> 129.89 | H66: =ROUND(G66,2) -> 129.89 | I66: =H66*E66 -> 7403.73 | J66: =G66-C66 -> 29.89 | K66: =I66-F66 -> 1703.73 | L66: =IF(F66<I66,(I66-F66),0) -> 1703.73 | M66: =IF(F66>I66,(I66-F66),0) -> 0 | N66: =M66+L66 -> 1703.73 | O66: Quantiy has exceeded WO Quantity, PM Approval is required for excess quantity
A68: b | B68: Ceramic Tile Flooring
A69: i | B69: Proving and Laying of 300 mm x 300mm Ceramic floor tiles (use Green Pro certified make approved by bank or CPC team as exception/ Refer make and model sheet,ceramic tiles) (1st quality) of approved make over a 75 mm thk cement mortar (use Green Pro certified make approved by bank or CPC team as exception/ Refer make and model sheet,cement section) bedding (1: 4) as per the pattern given including colour cement joints in matching shade. Rate to include curing, acid wash, etc. complete. The joints shall be kept as thin as possible not exceeding 1 mm. (Basic cost of tile Rs. 35/- Sq. ft) | D69: Sq.ft | E69: 76 | F69: =E69*C69 -> 0 | H69: =ROUND(G69,2) -> 0 | I69: =H69*E69 -> 0 | J69: =G69-C69 -> 0 | K69: =I69-F69 -> 0 | L69: =IF(F69<I69,(I69-F69),0) -> 0 | M69: =IF(F69>I69,(I69-F69),0) -> 0 | N69: =M69+L69 -> 0
A70: ii | B70: Similar to above but for providing and fixing 3" high skirting/border. | D70: R.ft | E70: 38 | F70: =E70*C70 -> 0 | H70: =ROUND(G70,2) -> 0 | I70: =H70*E70 -> 0 | J70: =G70-C70 -> 0 | K70: =I70-F70 -> 0 | L70: =IF(F70<I70,(I70-F70),0) -> 0 | M70: =IF(F70>I70,(I70-F70),0) -> 0 | N70: =M70+L70 -> 0
A72: c | B72: Granite Flooring
A73: i | B73: Supplying and laying 12 mm thk machine cut & machine polished Granite flooring , on a prefinished surface with 1:3 cement sand mortar (Green Pro certified make approved by bank or CPC team as exception/ Refer make and model sheet,cement section) .(Basic cost of granite Rs 180 /sq.ft). Rate shall be inclusive of machine polishing edges in case of protruding edges & groove if ordered. . Measurement for payment shall be as per laid area . | D73: Sq.ft | E73: 317 | F73: =E73*C73 -> 0 | H73: =ROUND(G73,2) -> 0 | I73: =H73*E73 -> 0 | J73: =G73-C73 -> 0 | K73: =I73-F73 -> 0 | L73: =IF(F73<I73,(I73-F73),0) -> 0 | M73: =IF(F73>I73,(I73-F73),0) -> 0 | N73: =M73+L73 -> 0
A74: ii | B74: Similar to above but 75mm high skirting/border. | D74: R.ft | E74: 128 | F74: =E74*C74 -> 0 | H74: =ROUND(G74,2) -> 0 | I74: =H74*E74 -> 0 | J74: =G74-C74 -> 0 | K74: =I74-F74 -> 0 | L74: =IF(F74<I74,(I74-F74),0) -> 0 | M74: =IF(F74>I74,(I74-F74),0) -> 0 | N74: =M74+L74 -> 0
A76: d | B76: Vitrified Tiles in wooden finish (in HNW areas with prior approval)
A77: i | B77: Same as item 9.a-(i) but vitrified tiles in wooden finish. (Green Pro certified make approved by bank or CPC team as exception/ Refer make and model sheet,vitrified floor tiles) (Basic cost of tile Rs.85/- per sq ft.) | D77: Sq.ft | E77: 122 | F77: =E77*C77 -> 0 | H77: =ROUND(G77,2) -> 0 | I77: =H77*E77 -> 0 | J77: =G77-C77 -> 0 | K77: =I77-F77 -> 0 | L77: =IF(F77<I77,(I77-F77),0) -> 0 | M77: =IF(F77>I77,(I77-F77),0) -> 0 | N77: =M77+L77 -> 0
A79: e | B79: Carpet Flooring (in HNW areas with prior approval)
A80: i | B80: Providing and laying carpet of 20 ounce loop pile in polypropylene in carpet tile (Green Pro certified make approved by bank or CPC team as exception/ Refer make and model sheet,vitrified floor tiles)form without underlay. Cost also included surface preparation required for laying of it and carpet protection. ( Basic cost of tile Rs.160 /- per sq ft.) | D80: Sq.ft | E80: 152 | F80: =E80*C80 -> 0 | H80: =ROUND(G80,2) -> 0 | I80: =H80*E80 -> 0 | J80: =G80-C80 -> 0 | K80: =I80-F80 -> 0 | L80: =IF(F80<I80,(I80-F80),0) -> 0 | M80: =IF(F80>I80,(I80-F80),0) -> 0 | N80: =M80+L80 -> 0
A82: f | B82: Vinyl Flooring
A83: i | B83: Providing fixing Vinyl Anti-Static flooring 5 mm thick Armstrong/LG/Tusker installed on smooth, hard & absolutely levelled sub-floor. Brushed SS edges shall be used at the seams. Conductive adhesives shall be used for fixing . | C83: 430 | D83: Sq.ft | E83: 105 | F83: =E83*C83 -> 45150 | G83: ='Measurement sheet'!F195 -> 418.5164 | H83: =ROUND(G83,2) -> 418.52 | I83: =H83*E83 -> 43944.6 | J83: =G83-C83 -> -11.4836 | K83: =I83-F83 -> -1205.4 | L83: =IF(F83<I83,(I83-F83),0) -> 0 | M83: =IF(F83>I83,(I83-F83),0) -> -1205.4 | N83: =M83+L83 -> -1205.4
A85: g | B85: False Flooring
A86: i | B86: P/F Raised access floor (false floor app. 150 mm to 230 mm high) .The panel shall be finished with antistatic 600x600x1.5mm laminate laid on base panels with solvent free epoxy, edge shall have 0.6mm PVC lipping & floor shall have UDL of 10 KN/Sq.m point load of 2.5 | C86: 80 | D86: Sq.ft | E86: 339 | F86: =E86*C86 -> 27120 | G86: ='Measurement sheet'!F200 -> 73.3244 | H86: =ROUND(G86,2) -> 73.32 | I86: =H86*E86 -> 24855.48 | J86: =G86-C86 -> -6.6756 | K86: =I86-F86 -> -2264.52 | L86: =IF(F86<I86,(I86-F86),0) -> 0 | M86: =IF(F86>I86,(I86-F86),0) -> -2264.52 | N86: =M86+L86 -> -2264.52
A87: ii | B87: P/F Raised access floor (false floor app. 300 mm high) .The panel shall be finished with antistatic 600x600x1.5mm laminate laid on base panels with solvent free epoxy, edge shall have 0.6mm PVC lipping & floor shall have UDL of 10 KN/Sq.m point load of 2.5 | D87: Sq.ft | E87: 350 | F87: =E87*C87 -> 0 | H87: =ROUND(G87,2) -> 0 | I87: =H87*E87 -> 0 | J87: =G87-C87 -> 0 | K87: =I87-F87 -> 0 | L87: =IF(F87<I87,(I87-F87),0) -> 0 | M87: =IF(F87>I87,(I87-F87),0) -> 0 | N87: =M87+L87 -> 0
A89: h | B89: POP covering on Flooring
A90: i | B90: Providing and applying POP covering on flooring for floor protection with plastic sheet between the flooring and POP. The rate should include the cleaning of POP and plastic on completion before handing over completed site. | D90: Sq.ft | E90: 12 | F90: =E90*C90 -> 0 | H90: =ROUND(G90,2) -> 0 | I90: =H90*E90 -> 0 | J90: =G90-C90 -> 0 | K90: =I90-F90 -> 0 | L90: =IF(F90<I90,(I90-F90),0) -> 0 | M90: =IF(F90>I90,(I90-F90),0) -> 0 | N90: =M90+L90 -> 0
A91: ii | B91: Providing and applying covering on flooring for floor protection with Heavy duty bubble sheet on newly placed flooring. The rate should include the cleaning of plastic on completion before handing over completed site. | C91: 2540 | D91: Sq.ft | E91: 12 | F91: =E91*C91 -> 30480 | G91: ='Measurement sheet'!F207 -> 2049.088 | H91: =ROUND(G91,2) -> 2049.09 | I91: =H91*E91 -> 24589.08 | J91: =G91-C91 -> -490.912 | K91: =I91-F91 -> -5890.92 | L91: =IF(F91<I91,(I91-F91),0) -> 0 | M91: =IF(F91>I91,(I91-F91),0) -> -5890.92 | N91: =M91+L91 -> -5890.92
A93: i | B93: Wall Dado Tiles
A94: i | B94: Proving and Laying Ceramic glaze Wall Tiles (Green Pro certified make approved by bank or CPC team as exception/ Refer make and model sheet,cement section) ( Colour : White ) of size 450mm x 300mm (1st quality) of somany make or approved make over a cement mortar bedding (1:4) (use Green Pro certified make approved by bank or CPC team as exception/ Refer make and model sheet,cement section) as per the pattern given including filling joint with colour cement in matching shade. (Basic cost of tiles Rs. 50/- Sq.ft). | D94: Sq.ft | E94: 76 | F94: =E94*C94 -> 0 | H94: =ROUND(G94,2) -> 0 | I94: =H94*E94 -> 0 | J94: =G94-C94 -> 0 | K94: =I94-F94 -> 0 | L94: =IF(F94<I94,(I94-F94),0) -> 0 | M94: =IF(F94>I94,(I94-F94),0) -> 0 | N94: =M94+L94 -> 0
A95: ii | B95: Proving and Laying wall dado Vitrified glaze tiles of size 600 mm X 600 mm (1st quality) of approved make over a cement mortar (Green Pro certified make approved by bank or CPC team as exception/ Refer make and model sheet,cement section) bedding (1:4) as per the pattern given including filling joint with colour cement in matching shade. (Basic cost of tiles upto Rs. 65/- Sq.ft). (Green Pro certified make approved by bank or CPC team as exception/ Refer make and model sheet, wall tiles) Somany : Delmon Beige - (600 x 600) | D95: Sq.ft | E95: 99 | F95: =E95*C95 -> 0 | H95: =ROUND(G95,2) -> 0 | I95: =H95*E95 -> 0 | J95: =G95-C95 -> 0 | K95: =I95-F95 -> 0 | L95: =IF(F95<I95,(I95-F95),0) -> 0 | M95: =IF(F95>I95,(I95-F95),0) -> 0 | N95: =M95+L95 -> 0
A97: 10 | B97: Pantry / Dining / Toilet Counter & Thresholds
A98: a | B98: Providing & fixing 600mm deep pantry counter made out of 12mm thk black granite supported by 25mm thk Kadappa to be fixed horizontally and vertically. The cost to be included of the platform to have 75mm wide granite fascia horizontally with molded edges as per design. 100mm high granite band over dado level to be provided. 75mm thk platform at floor level inside the counter should be provided finished with 75mm high granite skirting from outside The cost to include of making hole in the counter for fixing sink, End verticals to be fixed made of Kadappa and covered with granite to be provided as per the design. (Basic Cost of Granite 180/- sq.ft). Cost of Storage, CP fittings, SS sink are not included. | C98: 20 | D98: R.ft | E98: 2796 | F98: =E98*C98 -> 55920 | G98: ='Measurement sheet'!F210 -> 20 | H98: =ROUND(G98,2) -> 20 | I98: =H98*E98 -> 55920 | J98: =G98-C98 -> 0 | K98: =I98-F98 -> 0 | L98: =IF(F98<I98,(I98-F98),0) -> 0 | M98: =IF(F98>I98,(I98-F98),0) -> 0 | N98: =M98+L98 -> 0
A99: b | B99: Providing & Fixing Dining Counter with S.S Angle Bracket in approved Black Granite finish at ht. 750 mm from Finished Floor Level.(Depth of Counter 600 mm) (Basic Cost of Granite 180/- sq.ft) | D99: R.ft | E99: 1483 | F99: =E99*C99 -> 0 | H99: =ROUND(G99,2) -> 0 | I99: =H99*E99 -> 0 | J99: =G99-C99 -> 0 | K99: =I99-F99 -> 0 | L99: =IF(F99<I99,(I99-F99),0) -> 0 | M99: =IF(F99>I99,(I99-F99),0) -> 0 | N99: =M99+L99 -> 0
A100: c | B100: Providing & fixing wash basin counter in Toilets of 600 mm Deep made of 12 mm thk black granite supported on 25thk Kadappa base. 75 mm wide granite facia to be provided at the edge of the counter. The cost to include of making hole in the counter for fixing wash basin, Cost of CP fittings, Wash basin are not included. (Basic Cost of Granite 180/- sq.ft) | D100: R.ft | E100: 1815 | F100: =E100*C100 -> 0 | H100: =ROUND(G100,2) -> 0 | I100: =H100*E100 -> 0 | J100: =G100-C100 -> 0 | K100: =I100-F100 -> 0 | L100: =IF(F100<I100,(I100-F100),0) -> 0 | M100: =IF(F100>I100,(I100-F100),0) -> 0 | N100: =M100+L100 -> 0
A101: d | B101: Providing & Fixing of size 450mm X 900mm both sides polished divider for Urinal made of 12mm thk Black Granite embedded in the wall. The edges of the granite to be machine polished. | C101: 2 | D101: Nos. | E101: 1716 | F101: =E101*C101 -> 3432 | G101: ='Measurement sheet'!F213 -> 1 | H101: =ROUND(G101,2) -> 1 | I101: =H101*E101 -> 1716 | J101: =G101-C101 -> -1 | K101: =I101-F101 -> -1716 | L101: =IF(F101<I101,(I101-F101),0) -> 0 | M101: =IF(F101>I101,(I101-F101),0) -> -1716 | N101: =M101+L101 -> -1716
A102: e | B102: Providing & Laying 150mm wide Black Granite Threshold at ATM and Main Entrance. (Basic Cost of Granite 180/- sq.ft) | C102: 20 | D102: R.ft | E102: 211 | F102: =E102*C102 -> 4220 | G102: ='Measurement sheet'!F224 -> 29.41 | H102: =ROUND(G102,2) -> 29.41 | I102: =H102*E102 -> 6205.51 | J102: =G102-C102 -> 9.41 | K102: =I102-F102 -> 1985.51 | L102: =IF(F102<I102,(I102-F102),0) -> 1985.51 | M102: =IF(F102>I102,(I102-F102),0) -> 0 | N102: =M102+L102 -> 1985.51 | O102: Quantiy has exceeded WO Quantity, PM Approval is required for excess quantity
A103: f | B103: Providing & Laying 75 mm wide Black Granite Threshold for Toilets & Pantry. (Basic Cost of Granite 180/- sq.ft) | C103: 15 | D103: R.ft | E103: 177 | F103: =E103*C103 -> 2655 | G103: ='Measurement sheet'!F229 -> 11.5 | H103: =ROUND(G103,2) -> 11.5 | I103: =H103*E103 -> 2035.5 | J103: =G103-C103 -> -3.5 | K103: =I103-F103 -> -619.5 | L103: =IF(F103<I103,(I103-F103),0) -> 0 | M103: =IF(F103>I103,(I103-F103),0) -> -619.5 | N103: =M103+L103 -> -619.5
A105: 11 | B105: External Paving/Flooring/Window sill
A106: a | B106: Supplying and laying 20 mm thk glossy chequered tiles heavy duty external grade for paving on a prefinished surface with 1:3 cement (use Green Pro certified make approved by bank or CPC team as exception/ Refer make and model sheet,cement section) sand mortar over a 50 mm thk cement mortar bedding (1: 4) / PCC as per the design including colour cement float joints in matching shade. (Basic cost of tiles Rs.35 /- per sq. ft.) | D106: Sq.ft | E106: 91 | F106: =E106*C106 -> 0 | H106: =ROUND(G106,2) -> 0 | I106: =H106*E106 -> 0 | J106: =G106-C106 -> 0 | K106: =I106-F106 -> 0 | L106: =IF(F106<I106,(I106-F106),0) -> 0 | M106: =IF(F106>I106,(I106-F106),0) -> 0 | N106: =M106+L106 -> 0
A107: b | B107: Providing and laying inter locking Paver blocks (heavy duty) in two or more shades by excavating the existing surface by @ 150mm to 230mm and providing layer for gravel over the entire area and covering the same with a layer of graded sand limestone, screeding / sinner to the required slope and providing primer locking pave blocks. The rate is inclusive of PCC (1:2:4) bed at the edges of the pattern as per site conditions. (Basic cost of tiles Rs.40 /- per sq. ft.) | D107: Sq.ft | E107: 98 | F107: =E107*C107 -> 0 | H107: =ROUND(G107,2) -> 0 | I107: =H107*E107 -> 0 | J107: =G107-C107 -> 0 | K107: =I107-F107 -> 0 | L107: =IF(F107<I107,(I107-F107),0) -> 0 | M107: =IF(F107>I107,(I107-F107),0) -> 0 | N107: =M107+L107 -> 0
A108: c | B108: Providing and laying Kotah stone, flooring 25mm-30mm thk. Having sizes not less than 55cms x 55 cms in plain/ diamond pattern and bed of 1:6 cm including cement float filling joints with neat cement slurry, curing, polishing and clearing complete in all respect. (for strong room flooring) | D108: Sq.ft | E108: 110 | F108: =E108*C108 -> 0 | H108: =ROUND(G108,2) -> 0 | I108: =H108*E108 -> 0 | J108: =G108-C108 -> 0 | K108: =I108-F108 -> 0 | L108: =IF(F108<I108,(I108-F108),0) -> 0 | M108: =IF(F108>I108,(I108-F108),0) -> 0 | N108: =M108+L108 -> 0
A109: d | B109: Treads & risers of steps. Providing and laying in required position polished granite slab 18mm thk with machine cut and machine polish in CM 1:3 for treads/ risers of steps. The rate is inclusive of full rounded nosing for treads and 3 no's groove on treads complete in all respect. ' The granite to be fixed with adhesive (approved Low VOC/No VOC Adhesives to be used by Bank or CPC team as exception / Refer Make and Model sheet, Adhesives) in case the same is to be fixed on a plywood surface. (Basic cost of Jet black granite Rs. 180/- sq.ft.) | D109: Sq.ft | E109: 314 | F109: =E109*C109 -> 0 | H109: =ROUND(G109,2) -> 0 | I109: =H109*E109 -> 0 | J109: =G109-C109 -> 0 | K109: =I109-F109 -> 0 | L109: =IF(F109<I109,(I109-F109),0) -> 0 | M109: =IF(F109>I109,(I109-F109),0) -> 0 | N109: =M109+L109 -> 0
A110: e | B110: Sill & jambs to windows / Doors. Providing and laying in required positions granite, slab 12 mm thk (Single piece), of approved make & colour with machine, cut and machine polish up to 145mm wide ; in cement mortar (Green Pro certified make approved by bank or CPC team as exception/ Refer make and model sheet,cement section) of 1:3 for sills and jambs of windows .The rate is inclusive of full rounded molding at the edges from inside. (Basic cost of granite Rs. 180/- sq.ft.) | C110: 80 | D110: R.ft | E110: 194 | F110: =E110*C110 -> 15520 | G110: ='Measurement sheet'!F239 -> 85.04 | H110: =ROUND(G110,2) -> 85.04 | I110: =H110*E110 -> 16497.76 | J110: =G110-C110 -> 5.04 | K110: =I110-F110 -> 977.76 | L110: =IF(F110<I110,(I110-F110),0) -> 977.76 | M110: =IF(F110>I110,(I110-F110),0) -> 0 | N110: =M110+L110 -> 977.76 | O110: Quantiy has exceeded WO Quantity, PM Approval is required for excess quantity
A111: f | B111: Providing and laying jambs to door at required positions granite slab 12mm thk. Up to 2100mm in length (Double piece) and machine polish up to 145mm wide ; in cement mortar (Green Pro certified make approved by bank or CPC team as exception/ Refer make and model sheet,cement section) of 1:3 for jambs of door .The rate is inclusive of fillet rounded molding at the edges from inside. (Basic cost of granite Rs. 180/- sq.ft.) | C111: 70 | D111: R.ft | E111: 385 | F111: =E111*C111 -> 26950 | G111: ='Measurement sheet'!F246 -> 84 | H111: =ROUND(G111,2) -> 84 | I111: =H111*E111 -> 32340 | J111: =G111-C111 -> 14 | K111: =I111-F111 -> 5390 | L111: =IF(F111<I111,(I111-F111),0) -> 5390 | M111: =IF(F111>I111,(I111-F111),0) -> 0 | N111: =M111+L111 -> 5390 | O111: Quantiy has exceeded WO Quantity, PM Approval is required for excess quantity
A112: g | B112: Treads & risers of steps. Providing and laying in required position granite slab 12mm thk with machine cut and machine polish in 19 mm BWP Plywood (BWP Plywood which are "Free of Added Urea Formaldehyde" (required) approved by Bank or CPC team as exception / Refer Make and Model sheet, BWP Plywood) for treads/ risers of steps of internal staircase of branch. The rate is inclusive of full rounded nosing for treads and 3 no's groove on treads complete in all respect. ' The granite to be fixed with adhesive (approved Low VOC/No VOC Adhesives to be used by Bank or CPC team as exception / Refer Make and Model sheet, Adhesives) in case the same is to be fixed on a plywood surface. (Basic cost of granite Rs. 180/- sq.ft.) | D112: Sq.ft | E112: 396 | F112: =E112*C112 -> 0 | H112: =ROUND(G112,2) -> 0 | I112: =H112*E112 -> 0 | J112: =G112-C112 -> 0 | K112: =I112-F112 -> 0 | L112: =IF(F112<I112,(I112-F112),0) -> 0 | M112: =IF(F112>I112,(I112-F112),0) -> 0 | N112: =M112+L112 -> 0
A114: 12 | B114: Façade Treatment
A115: a | B115: P/F 12mm thk Black Granite to be fixed with approved adhesive (approved Low VOC/No VOC Adhesives to be used by Bank or CPC team as exception / Refer Make and Model sheet, Adhesives) and curing on plywood base (use Plywood which are "Free of Added Urea Formaldehyde" (required) and Green Pro certified (Mandatory) and make approved by Bank or CPC team as exception / Refer Make and Model sheet, BWR Plywood) paneling on the façade. (Cost of plywood paneling not included). (Basic cost of granite Rs. 180/- sq.ft.) | D115: Sq.ft | E115: 474 | F115: =E115*C115 -> 0 | H115: =ROUND(G115,2) -> 0 | I115: =H115*E115 -> 0 | J115: =G115-C115 -> 0 | K115: =I115-F115 -> 0 | L115: =IF(F115<I115,(I115-F115),0) -> 0 | M115: =IF(F115>I115,(I115-F115),0) -> 0 | N115: =M115+L115 -> 0
A117: 13 | B117: Handicapped Access Ramp
A118: a | B118: Providing and constructing handicapped ramp at a slope of 1:12 or as per site conditions with raised floor to be made by filling dubber stone soling and compacted by sand dust & 1:4 cement mortar ( Green Pro certified make approved by bank or CPC team as exception/ Refer make and model sheet, cement) to match the required level. The width of ramp should be minimum upto 1200mm | D118: R.ft | E118: 1114 | F118: =E118*C118 -> 0 | H118: =ROUND(G118,2) -> 0 | I118: =H118*E118 -> 0 | J118: =G118-C118 -> 0 | K118: =I118-F118 -> 0 | L118: =IF(F118<I118,(I118-F118),0) -> 0 | M118: =IF(F118>I118,(I118-F118),0) -> 0 | N118: =M118+L118 -> 0
A119: b | B119: Providing and constructing raised floor for staircase and midlanding by filling dubber stone soling and compacted by sand dust ,1:4 cement mortar (use Green Pro certified make approved by bank or CPC team as exception/ Refer make and model sheet,cement section) to match the required level. | D119: Sq.ft | E119: 271 | F119: =E119*C119 -> 0 | H119: =ROUND(G119,2) -> 0 | I119: =H119*E119 -> 0 | J119: =G119-C119 -> 0 | K119: =I119-F119 -> 0 | L119: =IF(F119<I119,(I119-F119),0) -> 0 | M119: =IF(F119>I119,(I119-F119),0) -> 0 | N119: =M119+L119 -> 0
A121: 14 | B121: Ramp Finishes
...

Sheet Measurement sheet
A1: HDFC BANK ICHALKARANJI (SECOND FLOOR) - MEASUREMENT SHEET
A2: Sr. No. | B2: PARTICULARS | C2: NO | D2: L | E2: B/D | F2: QTY | G2: Remark
A3: I | B3: CIVIL & RELATED WORKS
A4: 1 | B4: Demolition / Clearing Works
A5: ii | B5: Dismantling of existing dado tiles without plaster
B6: Hub Room Old Tiles | C6: 1 | D6: 10.52 | E6: 9 | F6: =C6*D6*E6 -> 94.68
C7: 1 | D7: 6.97 | E7: 9 | F7: =C7*D7*E7 -> 62.73
B8: Gents Washroom | C8: 1 | D8: 16.17 | E8: 9 | F8: =C8*D8*E8 -> 145.53
B9: Pantry | C9: 1 | D9: 12 | E9: 9 | F9: =C9*D9*E9 -> 108
B10: Conference Room | C10: 1 | D10: 18.33 | E10: 9 | F10: =C10*D10*E10 -> 164.97
B11: CH Cabin Wall | C11: 1 | D11: 5.36 | E11: 9 | F11: =C11*D11*E11 -> 48.24
B12: RM Wall | C12: 1 | D12: 5.36 | E12: 9 | F12: =C12*D12*E12 -> 48.24
B13: RM near Window | C13: 1 | D13: 8 | E13: 3 | F13: =C13*D13*E13 -> 24
B14: RM Area Column 1 & 2 | C14: 2 | D14: 3.5 | E14: 9 | F14: =C14*D14*E14 -> 63
B15: RM Area Cloumn 3, 4 & 5 | C15: 3 | D15: 2 | E15: 9 | F15: =C15*D15*E15 -> 54 | G15: Photos and CAD File with marking
B16: Server Window Granite 7 x 3 | C16: 1 | D16: 20 | E16: 0.5 | F16: =C16*D16*E16 -> 10
B17: Store Window Granite 4 x 3 | C17: 1 | D17: 48 | E17: 0.5 | F17: =C17*D17*E17 -> 24
B18: Store Door Frame 7 x 3 | C18: 1 | D18: 20 | E18: 0.5 | F18: =C18*D18*E18 -> 10
B19: Ladies Window Granite 5.5 x 4 | C19: 1 | D19: 19 | E19: 0.5 | F19: =C19*D19*E19 -> 9.5
B20: Gents Window Granite 2 x 3 | C20: 1 | D20: 10 | E20: 0.5 | F20: =C20*D20*E20 -> 5
B21: Gents Window Granite 4 x 4 | C21: 1 | D21: 16 | E21: 0.5 | F21: =C21*D21*E21 -> 8
B22: Pantry Window Granite 4 x 4 - 2nos / 5.5 x 4 / 2 x 3 | C22: 1 | D22: 45 | E22: 0.5 | F22: =C22*D22*E22 -> 22.5
B23: Conf Window Granite 2 x 3 - 4nos | C23: 1 | D23: 40 | E23: 0.5 | F23: =C23*D23*E23 -> 20
B24: CH Window Granite 2 x 3 | C24: 1 | D24: 10 | E24: 0.5 | F24: =C24*D24*E24 -> 5
B25: RM Window Granite 2 x 3 | C25: 1 | D25: 10 | E25: 0.5 | F25: =C25*D25*E25 -> 5
C26: TOTAL | F26: =SUM(F6:F25) -> 932.39
A27: iii | B27: Dismantling of existing plaster
B28: Store Room | C28: 1 | D28: 8.95 | E28: 9 | F28: =C28*D28*E28 -> 80.55
B29: Deduction - Door | C29: -1 | D29: 3 | E29: 6.82 | F29: =C29*D29*E29 -> -20.46
B30: Ladies Washroom | C30: 1 | D30: 5.36 | E30: 9 | F30: =C30*D30*E30 -> 48.24 | G30: Photos and CAD FILE with marking
B31: Pantry | C31: 1 | D31: 10.78 | E31: 9 | F31: =C31*D31*E31 -> 97.02
B32: Deduction - Window | C32: -1 | D32: 5.79 | E32: 3.77 | F32: =C32*D32*E32 -> -21.8283
B33: Hub Entry Column | C33: 1 | D33: 2 | E33: 9 | F33: =C33*D33*E33 -> 18
B34: Graphic Wall | C34: 1 | D34: 28.69 | E34: 9 | F34: =C34*D34*E34 -> 258.21
C35: TOTAL | F35: =SUM(F28:F34) -> 459.7317
A36: iv | B36: Existing flooring including bedding material & PCC/IPS.
B37: Hub Room | C37: 1 | D37: 12 | E37: 2 | F37: =C37*D37*E37 -> 24
B38: Ladies Washroom | C38: 1 | D38: 7.93 | E38: 5.45 | F38: =C38*D38*E38 -> 43.2185
B39: Deduction - Column | C39: -1 | D39: 1.54 | E39: 2.5 | F39: =C39*D39*E39 -> -3.85
B40: Gents Washroom | C40: 1 | D40: 10.42 | E40: 5.75 | F40: =C40*D40*E40 -> 59.915
B41: Pantry near Wash Basin | C41: 1 | D41: 9 | E41: 9.25 | F41: =C41*D41*E41 -> 83.25
B42: Conference Room | C42: 1 | D42: 10 | E42: 9 | F42: =C42*D42*E42 -> 90
C43: 1 | D43: 7 | E43: 2.5 | F43: =C43*D43*E43 -> 17.5
B44: CH Cabin | C44: 1 | D44: 5 | E44: 7 | F44: =C44*D44*E44 -> 35
B45: RM | C45: 1 | D45: 5 | E45: 7 | F45: =C45*D45*E45 -> 35
B46: RM near Window | C46: 1 | D46: 19.6 | E46: 8 | F46: =C46*D46*E46 -> 156.8
C47: TOTAL | F47: =SUM(F37:F46) -> 540.8335
A48: v | B48: Existing Doors / Windows
B49: Windows - Server / Store / Ladies / Gents -2 / Pantry -4 / Conf- 4 / CH / RM | F49: 15 | G49: Photos and CAD FILE with marking
B50: Door - Pantry | F50: 1
C51: TOTAL | F51: =SUM(F49:F50) -> 16
A52: xii | B52: Dismantling of existing RCC 6 "/ 9" thk wall.
B53: For Plumbing | C53: 2 | D53: 1 | E53: 1 | F53: =C53*D53*E53 -> 2
C54: TOTAL | F54: =SUM(F53) -> 2
A55: 2 | B55: Construction of Masonry Walls
A56: d | B56: Do-do as 2(a) above but 150mm thk siporex / AAC / Aerocon / light weight block wall
B57: Hub Room Window | C57: 1 | D57: 7 | E57: 3 | F57: =C57*D57*E57 -> 21 | G57: Photos
B58: Hub Room Entry | C58: 1 | D58: 6.97 | E58: 9 | F58: =C58*D58*E58 -> 62.73
B59: Deduction - Door | C59: -1 | D59: 3.2 | E59: 7.15 | F59: =C59*D59*E59 -> -22.88
B60: Hub Room | C60: 1 | D60: 10.52 | E60: 10.25 | F60: =C60*D60*E60 -> 107.83
B61: Electric Room | C61: 1 | D61: 6.94 | E61: 10.25 | F61: =C61*D61*E61 -> 71.135
B62: Utility Entry | C62: 1 | D62: 18.94 | E62: 9 | F62: =C62*D62*E62 -> 170.46
B63: Deduction - Door | C63: -1 | D63: 2.75 | E63: 6.82 | F63: =C63*D63*E63 -> -18.755
B64: Store Room Wall | C64: 1 | D64: 10.53 | E64: 10.25 | F64: =C64*D64*E64 -> 107.9325
B65: Deduction - Door | C65: -1 | D65: 2.75 | E65: 6.82 | F65: =C65*D65*E65 -> -18.755
B66: Gents Wall | C66: 1 | D66: 10.42 | E66: 10.25 | F66: =C66*D66*E66 -> 106.805
B67: Deduction - Door | C67: -1 | D67: 2.75 | E67: 6.82 | F67: =C67*D67*E67 -> -18.755
B68: Ladies Entry Wall | C68: 1 | D68: 7.94 | E68: 10.25 | F68: =C68*D68*E68 -> 81.385
B69: Deduction - Door | C69: -1 | D69: 2.75 | E69: 6.82 | F69: =C69*D69*E69 -> -18.755
... B71: Ladies Wall Near Column | C71: 1 | D71: 1.5 | E71: 10.25 | F71: =C71*D71*E71 -> 15.375
B72: Ladies Window | C72: 1 | D72: 5.5 | E72: 4 | F72: =C72*D72*E72 -> 22 | G72: Photo
B73: Gents Window | C73: 1 | D73: 4 | E73: 2 | F73: =C73*D73*E73 -> 8 | G73: Photo
B74: Pantry Wall | C74: 1 | D74: 11.77 | E74: 10.25 | F74: =C74*D74*E74 -> 120.6425
B75: Pantry Window | C75: 1 | D75: 3 | E75: 2 | F75: =C75*D75*E75 -> 6 | G75: Photos
B76: Conf Window | C76: 4 | D76: 3 | E76: 2 | F76: =C76*D76*E76 -> 24 | G76: Photos
B77: CH Windpw | C77: 1 | D77: 3 | E77: 2 | F77: =C77*D77*E77 -> 6 | G77: Photos
B78: RM Window | C78: 1 | D78: 3 | E78: 2 | F78: =C78*D78*E78 -> 6 | G78: Photos
B79: Misc | F79: =C79*D79*E79 -> 0
C80: TOTAL | F80: =SUM(F57:F79) -> 851.395
A81: 4 | B81: Plaster
A82: a | B82: P/A 1:4 cement plaster
B83: Wall Construction | C83: 2 | D83: 1 | E83: =F80 -> 851.395 | F83: =C83*D83*E83 -> 1702.79 | G83: Need to check
B84: Ladies Column | C84: 1 | D84: 2 | E84: 10.25 | F84: =C84*D84*E84 -> 20.5
B85: Existing Wall in Ladies Column | C85: 1 | D85: 5.36 | E85: 9 | F85: =C85*D85*E85 -> 48.24
B86: Deduction - Window | C86: -1 | D86: 5.5 | E86: 4 | F86: =C86*D86*E86 -> -22
C87: -1 | D87: 2 | E87: 3 | F87: =C87*D87*E87 -> -6
B88: Existing Wall in Gents | C88: 1 | D88: 17 | E88: 9 | F88: =C88*D88*E88 -> 153
B89: Deduction - Window | C89: -1 | D89: 1.5 | E89: 2.2 | F89: =C89*D89*E89 -> -3.3
C90: -1 | D90: 1.5 | E90: 1.5 | F90: =C90*D90*E90 -> -2.25
B91: Pantry Wall | C91: 1 | D91: 20.02 | E91: 9 | F91: =C91*D91*E91 -> 180.18
B92: Deduction - Windows | C92: -1 | D92: 3.71 | E92: 3.69 | F92: =C92*D92*E92 -> -13.6899
B93: Deduction - Windows | C93: -1 | D93: 3.76 | E93: 3.54 | F93: =C93*D93*E93 -> -13.3104
B94: Conference Room | C94: 1 | D94: 18.33 | E94: 9 | F94: =C94*D94*E94 -> 164.97
B95: Deduction - Windows | C95: -4 | D95: 2 | E95: 3 | F95: =C95*D95*E95 -> -24
B96: CH Cabin | C96: 1 | D96: 6.5 | E96: 9 | F96: =C96*D96*E96 -> 58.5 | G96: Photo
B97: RM Area | C97: 1 | D97: 6.5 | E97: 9 | F97: =C97*D97*E97 -> 58.5 | G97: Photo
B98: RM Arear near Window | C98: 1 | D98: 5 | E98: 3 | F98: =C98*D98*E98 -> 15 | G98: Photo
B99: Misc | F99: 0
C100: TOTAL | F100: =SUM(F83:F99) -> 2317.1297
A101: 5 | B101: Waterproofing treatment
...

Sheet Debit
A1: U.Code | B1: Sr.No | C1: Particulars | D1: Unit | E1: Rate | F1: Earlier Qty | G1: Eariler Amount | H1: Revised Qty as per CWI | I1: Final Amount | J1: Remarks
C3: Civil & related works
A4: i | B4: i | C4: Providing and fixing in place, branch manager's table of size 1575mm x 675mm(worktop size)comprising of 25mm thick table top made of medium density particle board with side credenza of size 400mm deep and 900mm long having sliding shutters with locks ( Make : Ebco ) and a 3 drawer pedestal of size 400mm x 500 mm x700mm consisting of 2nos. drawer of 150mm deep and 300mm deep filing drawer having common lock ( Make : Ebco ) including modesty apron to be made out of 19mm thick BWR plywood (use Plywood which are "Free of Added Urea Formaldehyde" (required) and Green Pro certified (Mandatory) and make approved by Bank or CPC team as exception / Refer Make and Model sheet, BWR Plywood) /high Density particle board. The table top to have post form edge. All complete including key board drawer, M.S. Powder coated Cable tray to place electrical sockets on it, CPU trolley and necessary hardware .( Make : Ebco) all the external surfaces to be finished with 1.0mm thick laminate and internal surfaces to be finished with 0.8 mm thick laminate of approved shade. all complete as directed.( All furniture hardware should be Ebco Make ) | D4: Nos | E4: 28249 | F4: 2 | G4: =F4*E4 -> 56498 | H4: =F4-0.25 -> 1.75 | I4: =H4*E4 -> 49435.75 | J4: A 25% debit has been imposed due to the non-provision of the keyboard tray and 3-drawer pedestal as per the approved specifications and the quantity has been rounded off accordingly
A5: III_5.b.iii | B5: iii | C5: same as item 5(a) above but size of the worktable to be 1200mm x 675mm with drawer pedestal and without side credenza. | E5: 20488 | F5: 8 | G5: =F5*E5 -> 163904 | H5: 7.65 | I5: =H5*E5 -> 156733.2 | J5: A debit of ₹900 has been imposed due to the non-provision of the keyboard tray as per the approved specifications, and the quantity has been rounded off accordingly
A6: III_5.d.i | B6: i | C6: Providing and fixing in place 600mm deep running counter made of medium density particle board with post form edge profile for 25mm thick table top, Consisting of a 3 drawer pedestal of size 400mm x 500 mm x700mm consisting of 2nos. drawer of 150mm deep and 300mm deep filing drawer having common lock ( Make : Ebco ) including modesty apron to be made out of 19mm thick BWR plywood (use Plywood which are "Free of Added Urea Formaldehyde" (required) and Green Pro certified (Mandatory) and make approved by Bank or CPC team as exception / Refer Make and Model sheet, BWR Plywood) /high particle board. All complete including key board drawer, M.S. Powder coated Cable tray to place electrical sockets on it, CPU trolley and necessary hardware.All the exposed surfaces to be finished with 1.0mm thick laminate.( All furniture hardware should be Ebco Make ) | E6: 16568 | F6: 2 | G6: =F6*E6 -> 33136 | H6: 1.89 | I6: =H6*E6 -> 31313.52 | J6: A debit of ₹900 has been imposed due to the non-provision of the keyboard tray as per the approved specifications, and the quantity has been rounded off accordingly
A7: III_5.e.i | B7: i | C7: Providing and fixing welcome desk consisting of two worktops (laminate and glass/granite) with a cabinet to house FRFC made of 19mm thick BWR plywood top, sides finished in 1.0mm thick laminate of approved shade. The table shall have a 3 drawer pedestal of size 400mm x 500 mm x700mm consisting of 2nos. drawer of 150mm deep and 300mm deep filing drawer having common lock ( Make : Ebco ) including modesty apron to be made out of 19mm thick BWR plywood (use Plywood which are "Free of Added Urea Formaldehyde" (required) and Green Pro certified (Mandatory) and make approved by Bank or CPC team as exception / Refer Make and Model sheet, BWR Plywood) /high particle board. with key boards and CPU stand complete with all hardware etc. all the exposed edges to have wooden lipping stained to match the laminate and Melaminee finished. all the internal surfaces to be hand Melamine Polished. ( All furniture hardware should be Ebco Make ) | E7: 24336 | F7: 1 | G7: =F7*E7 -> 24336 | H7: 0.96 | I7: =H7*E7 -> 23362.56 | J7: A debit of ₹900 has been imposed due to the non-provision of the keyboard tray as per the approved specifications, and the quantity has been rounded off accordingly
A8: III_5.f.i | B8: i | C8: P/f Double level teller counter made out of 19mm thick plywood (use Plywood which are "Free of Added Urea Formaldehyde" (required) and Green Pro certified (Mandatory) and make approved by Bank or CPC team as exception / Refer Make and Model sheet, BWR Plywood) and finished in laminate one at 750mm and other at 1200mm level. Top level counter to be finished in jet black granite with double molding. The upper most worktop to have vertical barriers in form of 8 mm thick toughen glass mounted on ss finish fabricated brackets for cash transactions. Teller to be provided with 4 nos. equal sized drawers, one key board at every 1200mm length. There should be a vertical barrier separating the adjacent counter at every 1200mm length. All the exposed surfaces to be finished with 1.0mm thick laminate and internal surfaces to be finished with hand Melamine Polish. all 5 S compliances as per bank's requirements to be followed. ( All furniture hardware should be Ebco Make ) | D8: R.ft | E8: 3813 | F8: 4.44 | G8: =F8*E8 -> 16929.72 | H8: 4.2 | I8: =H8*E8 -> 16014.6 | J8: A debit of ₹900 has been imposed due to the non-provision of the keyboard tray as per the approved specifications, and the quantity has been rounded off accordingly
C12: ELECTRIFICATION AND ALLIED WORKS
A13: VI_1.1.2 | B13: 1.1.2 | C13: TYPE I PANEL - Main LT Panel (For 1500-2500 sq. ft) | D13: Nos | E13: 155313 | F13: 1 | G13: =F13*E13 -> 155313 | H13: =F13-0.065 -> 0.935 | I13: =H13*E13 -> 145217.65 | J13: A 6% debit has been imposed due to the non-provision of 1 No. 32A TPN MCB and 1 No. 80A TP MCCB (Incomer) as per the approved specification.

Sheet Documnets
A1: Sr. No | B1: Description | C1: Unit | D1: Qty Claimed | E1: Photos and Documents Requird
A2: Demolition / Clearing Works
A3: 1 | B3: Dismantling of existing dado tiles without plaster | C3: Sq.ft | D3: 932.39 | E3: Photos required & Existing Layout with Marking and CAD File
A4: 2 | B4: Dismantling of existing plaster | C4: Sq.ft | D4: 459.73 | E4: Photos required & Existing Layout with Marking and CAD File
A5: 3 | B5: Existing flooring including bedding material & PCC/IPS. | C5: Sq.ft | D5: 540.83 | E5: Photos required
A6: 4 | B6: Windows and Door | C6: Nos | D6: 16 | E6: Photos required & Existing Layout
A7: 5 | B7: Dismantling of existing RCC 6 "/ 9" thk wall. | C7: Sq.ft | D7: 2 | E7: Photos required
A8: 6 | B8: Construction of Masonry Walls
B9: Hub Room Window | C9: Sq.ft | D9: 21 | E9: Photos required
B10: Ladies Window | C10: Sq.ft | D10: 22
B11: Gents Window | C11: Sq.ft | D11: 8
B12: Pantry Window | C12: Sq.ft | D12: 6
B13: Conf Window | C13: Sq.ft | D13: 24
B14: CH Windpw | C14: Sq.ft | D14: 6
B15: RM Window | C15: Sq.ft | D15: 6
A16: 7 | B16: Plaster
B17: CH Cabin | C17: Sq.ft | D17: 58.5
B18: RM Area | C18: Sq.ft | D18: 58.5
B19: RM Arear near Window | C19: Sq.ft | D19: 15
A20: 8 | B20: Waterproofing Photos | C20: Sq.ft | D20: 285.08 | E20: Photos required
A21: 9 | B21: Brickbat work | C21: Sq.ft | D21: 109.28 | E21: Photos required
A22: 10 | B22: PCC Work | C22: Sq.ft | D22: 534.5 | E22: Photos required
A23: 11 | B23: POP covering on Flooring | C23: Sq.ft | D23: 2191.5 | E23: Photos required Staircase Area As well
A24: 12 | B24: Trenching work as per width and depth required. | C24: R.ft | D24: 190 | E24: Photos required
A25: 13 | B25: Making punctures in existing brick/siporex block up to 200mm diameter, | C25: Nos | D25: 1 | E25: Photos required
A26: 14 | B26: MS H Type Frame | C26: Sq.ft | D26: 350 | E26: Photos required
A27: 15 | B27: C02 Monitoring | C27: Nos | D27: 3 | E27: Pending
A28: 16 | B28: POP Punning - Graphic Wall | C28: Sq.ft | D28: 49.76 | E28: Photos required
A29: 17 | B29: 600mm x 600mm Modular Grid Ceiling : Around AC in Pantry | E29: Photos required
A30: 18 | B30: Washroom Antilobby Door Glass fixed Photos | C30: Nos | D30: 1 | E30: Photos required
A31: 19 | B31: For 3 Phase UPS 40 Amp MCB to 63 AMP MCB Change | C31: Nos | D31: 1 | E31: Geo Tag Photos required
A32: 20 | B32: TPN, 8 Way (above 2500 Sq. ft area) 40 Amp MCB to 63 AMP MCB Change | C32: Nos | D32: 1 | E32: Geo Tag Photos required
A33: 21 | B33: TPN, 8 Way (above 2500 Sq. ft area) -40 Amp MCB to 63 AMP MCB Change | C33: Nos | D33: 1 | E33: Geo Tag Photos required
A34: 22 | B34: 6 amps Light Plug Outlets :- Conference Room | C34: Nos | D34: 4 | E34: Geo Tag Photos required
A35: 23 | B35: Wooden Fire Rated Door | E35: Certficate Required
A36: 24 | B36: All Inovices (Including Painting Plumbing, Eletrical,Carpentry, Waterproofing, Cement, Blockwork, Tuffen glass, Modular) | E36: As mentioned, all required invoices
A37: 25 | B37: Glazed Glass Invoice
A38: 26 | B38: Frosted Film
A39: 27 | B39: IGBC | E39: Required Product Certficate that has been used in the branch
A40: 28 | B40: CAR and WC | E40: Policies

Sheet Make and Models
A1: LIST OF MATERIALS & APPROVED BRANDS FOR HDFC Bank
B2: Material | C2: IMP Criteria | D2: Approved brands
B3: Civil Items
A4: 1 | B4: Cement | C4: Green Pro Certification | D4: ACC 1. ACC Suraksha Power 2. ACC Gold Water Shield 3. ACC F2R Superfast 4. ACC HPC Long Life 5. ACC Concrete+ Xtra Strong JK Lakshmi Cement Ltd 1. COC 2. PPC 3. Sixer 4. HDP 5. PHDP 6. Platinum 7. PSC 8. PRO Plus UltraTech Cement Limited 1. UltraTech Premium, Composite Cement 2. UltraTech Weather Plus, Composite Cement 3. UltraTech Weather Plus, Portland Pozzolana Cement 4. UltraTech, Composite Cement 5. UltraTech, Portland Pozzolana Cement Dalmia Cement 1. Vajram Cement - Portland Pozzolana Cement (PPC) JSW Cement Ltd 1. portland Slag Cement 2. Composite Cement
A5: 2 | B5: Ready Mixed Concrete | C5: Green Pro Certification | D5: ACC : ACC ECOPACT ACC Feathercrete ACC Fillcrete ACC Flowcrete ACC Permicrete ULTRATECH : Ultratech Duracon Ultratech Flowfill Ultratech Free flow Ultratech Hypercon
A6: 3 | B6: Aerocon Block | C6: Green Pro Certification | D6: Ultra Tech 1. Extralite- AAC Blocks JK Lakshmi Cement Ltd 1.JK Smartblox Godrej 1. Tuff Blocks JVS Comatsco Industries Pvt. Ltd 1. Ecolite AAC Blocks KD Infra 1.Brikolite AAC Block UAL Industries Ltd 1.KON_CRETE AAC blocks UltraTech Cement Limited 1. Xtralite - AAC Blocks Zuari Cement Limited 1. Super lite- AACblocks
A7: 4 | B7: Waterproofing | C7: NA | D7: Pedilite /Roff
A8: 5 | B8: False Flooring | C8: NA | D8: United insulation /Flexi floor (aet) / Kebao / Innerspace
A9: 6 | B9: Bubble sheet | C9: NA | D9: Cello
A10: 7 | B10: SS Sink | C10: NA | D10: Nirali
A11: 8 | B11: Sanitarywares & Faucets
A12: 8.01 | B12: Pillar cock | C12: Water Flow Rate at 3 Bar pressure | D12: Jaguar Use Jaquar Make with model no. 021KNG with flow rate of 2.5 LPM @ pressure of 3 Bar. Pl note Suffix G in model no. is critical to get desired flow rate. Cera F2013101- FOUNTAIN - Pillar cock with aerator F1001101- PLATINUM - Pillar cock with aerator F1015101-VICTOR - Pillar cock with aerator Hindware : F730002CP : Contessa Neo Pillar Cock Long Neck F740001CP : Dove Pillar cock
A13: 8.02 | B13: Sink cock | C13: Water Flow Rate at 3 Bar pressure | D13: Jaguar Use Jaquar Make and same model with Suffix GD (like 349 KNGD) with flow rate of 3.8 LPM @ pressure of 3 Bar. Pl note Suffix GD in model no. is critical to get desired flow rate. Cera F1016251-CHELSEA - Sink cock (wall mounted) with 200 mm (8″) long swivel spout and wall flange F1002251 - CARBON - Sink cock (wall mounted) with 150 mm (6″) long swivel spout and aerator F2013251 - FOUNTAIN - Sink cock (wall mounted) with 150 mm (6″) long swivel spout and aerator Hindware F200024CP :Classik Sink Cock With Swivel Casted Spout (Wall Mounted) F120021CP :Axxis Sink Cock With Normal Swinging Spout (Wall Mounted)
A14: 8.03 | B14: Two way bib cock | C14: Water Flow Rate at 3 Bar pressure | D14: Jaguar Use Jaquar Make with model no. 043NG with flow rate of 2.5 LPM @ pressure of 3 Bar. Pl note Suffix G in model no. is critical to get desired flow rate. Cera F2013163-FOUNTAIN - 2-way Bib cock with single handle and wall flange F1003161- TITANUM - 2-Way bib cock with wall flange and aerator Hindware : F200004CP :Classik Bib Cock 2 In 1 F120003CP :Axxis Bib Cock 2 In 1
A15: 8.04 | B15: Angle cock | C15: NA | D15: Jaguar : CON-CHR-059KN Hindware : F200005CP :Classik Angular Stop Cock
A16: 8.05 | B16: Concealed stop cock | C16: NA | D16: Jaguar : CON-CHR-083FTK Hindware : F200007CP : Classik Concealed Stop Cock- 15 / 20 mm
A17: 8.06 | B17: Urinal - Flush Valve | C17: Water Flow Rate | D17: Jaguar Use Jaquar Make with model no. 077G with flow rate of 1.5 LPF. Pl note Suffix G in model no. is critical to get desired flow rate. Cera - F9020203 : Self closing angle cock pressmatic for urinal with wall flange and 200 mm connecting pipe
A18: 8.07 | B18: Tower rail (450 mm) | C18: NA | D18: ACN-1111BNM
A19: 8.08 | B19: Towel ring | C19: NA | D19: ACN-CHR-1121N
A20: 8.09 | B20: Soap dispenser | C20: NA | D20: ACN-CHR-1135N
A21: 8.1 | B21: Toilet roll holder | C21: NA | D21: ACN-CHR-1153S
A22: 8.11 | B22: Hook | C22: NA | D22: ANC-1161N
A23: 8.12 | B23: Jet spray | C23: Water Flow Rate at 3 Bar pressure | D23: Jaguar Use Jaquar Make with model no. 565GA with flow rate of 6 LPM @ pressure of 3 Bar. Pl note Suffix GA in model no. is critical to get desired flow rate. Cera F8030101 / F8030102 / F8030103 / F8030104AB /F8030105AB / F8030109AB - Health Faucet ABS body with 1 meter SS braided connection pipe
... A27: 8.16 | B27: SS Sink | C27: NA | D27: Nirali - Grace plain - Small (485mm x 410mm) glossy
A28: 8.17a | B28: Wall hung Water closet (Ceramic Fitting) | C28: Green Pro Certification | D28: Hindware - ATHENS One Piece Closet 92511/ Mario Extended Wall Mounted Closet 20084 / Element 92082 /Florence Coupled Closet 92058 / Constellation Extended Wall Mounted Closet 20028. Cera - CAMPBELL S1021109 S Trap 120 mm S1021110 P Trap/ CURTIS S1031111 P Trap /
A29: 8.17b | B29: Water Closet With Flush Valve | C29: Water Flow rate | D29: Jaguar Suggesting use of jaguar make with model number 1085G, 1085SQG, 1085DFPG, 1089G, 1089SQG, 1089DFPG (for flush valves) with flow rates of 4/2 LPF. Pl note Suffix G in model no is critical to get desired flow rate. Cera: F8010106 : Flush valve concealed push type (Double flow) 25 mm (1”) 4/2 LPF
A30: 8.17c | B30: Water Closet With Cistern | C30: Water Flow rate | D30: Cera S1021103 + S1060101 - Calibre deluxe ewc-S + Calibre cistern S1021104 + S1060104 -Callaghan two pc ewc-S + Callaghan cistern S1013110 - Campbell one pc ewc-S 110 mm S1021120 + B1020105 - Curtis two pc ewc-S S1021113 + S1060106 - Cruse two pc ewc-S S1041105 - Compact wall hung S1031111 + B1020105 - Curtis wall hung with Curtis PVC Cistern S1021132 + S1060122 - Cimberly two piece Water closet-S trap with Cimberly cistern Hindware Cleo - S-190/220 ESSENCE - 92051 ENIGMA SLIM 92502 ELEMENT 92081
A31: 8.19 | B31: Wall mounted / Table top Wash basin | C31: Green Pro Certification | D31: Hindware - Compac 10004 / Cleo 10012 WHITE CERA Wash basins - CHIME S2040139 / CAMMY : S2090127 / CORBA : S2020104
A32: 8.2 | B32: Urinal | C32: Green Pro Certification | D32: CERA Sanitaryware - URINAL Urinal Flat Back with integrated EFS 360 x 330 x 740 mm (S4010101) Hindware : 60020 : FB- Eureka Standard Urinal
A33: 8.21 | B33: Under counter wash basin | C33: NA | D33: Hindware Round 10065 / Zen 10049 WHITE / Cera
A34: 10 | B34: PVC/ CPVC/UPVC pipe | C34: NA | D34: Astral / Prince / Precision
A35: 11 | B35: Anti Termite | C35: NA | D35: PCI / Hicare
B37: Flooring
A38: 1 | B38: Tiles | C38: Green Pro Certification | D38: Somany : Ultra Charge -Vitro - Milky White (800 x 800) Ultra charge - Vitro - Berlineta White ( 800 x 800 ) Delmon Beige - (600 x 600) Prism Johnson JOHNSON MARBONITE - DOUBLE CHARGE JOHNSON REFLECTO Nitco Duracottura Tiles Wall Tiles
A39: 3 | B39: Vinyl Flooring | C39: NA | D39: Armstrong/Tusker
B41: Carpentry Items
A42: 1 | B42: BWR Plywood | C42: Green Pro Certification | D42: Vidya Ply and Board Pvt Ltd , Samrat,
A43: 1.1 | B43: Commercial Plywood Plywood with "Free of Urea Formaldehyde" | C43: Free of Urea Formaldehyde , FSC Certified, IGBC Registered | D43: Century,V-CAN,Green Ply
A44: 2 | B44: Marine Plywood Plywood with "Free of Urea Formaldehyde" | C44: Free of Urea Formaldehyde , FSC Certified, IGBC Registered | D44: Century, Samrat, V-CAN,Green Ply,
A45: 4 | B45: Partition Framework | C45: NA | D45: Aluminium sections / India Gypsum : GI METAL FRAME PARTITION SYSTEM
A46: 5 | B46: Block Board | C46: Free of Urea Formaldehyde , FSC Certified, IGBC Registered | D46: Century,Samrat, V-CAN, Vidya Ply and Board Pvt Ltd,Green Ply,
A47: 6 | B47: Gypsum Board | C47: Green Pro Certification | D47: Gyproc Saint Gobin : Gypboard Plain Gypboard Fireline Board India Gypsum : Regular Gypsum Board Fire Resistance Gypsum Board USG Boral :
A48: 7 | B48: Bison Board | C48: NA | D48: Bison
A49: 8 | B49: Flush Door | C49: Free of Urea Formaldehyde , FSC Certified, IGBC Registered | D49: Century,Green Ply, Samrat,
A50: 9 | B50: Laminate | D50: Century,Green lam, Samrat, Royal Touch,
A51: 9a | B51: Laminate Shade | C51: Green Certification & IGBC Registered | D51: Century Lam : # 525 - Fusion Maple Samrat : 485SF #Light Bavarian Beech and 816SF #Mangfall Beech
A52: 10 | B52: Adhesive For Wood | C52: Low VOC or No VOC as per IGBC Norms | D52: Fevicol SH / Marine/ Hiper
A53: 11 | B53: Rubberized Adhesive | C53: Low VOC or No VOC as per IGBC Norms | D53: Fevicol SR / Fevicol Heatx / Ezee Spray / SR-998
A54: 12 | B54: Clear Float Glass, Toughened glass | C54: Green Pro Certification | D54: Saint Globain
A55: 13 | B55: Back Painted Glass | C55: Green Pro Certification | D55: Saint Globain - Titanium Gray Asahi : Stone Grey and Sparling Snow White
A56: 14 | B56: Full glazed toughened glass partition | C56: Green Pro Certification | D56: Saint Globain/Asahi / Modiguard
A57: 15 | B57: Frame toughened glass door fitting | C57: Green Pro Certification | D57: Saint Globain/Asahi / Modiguard
A58: 16 | B58: Acrylic Solid surface | C58: NA | D58: LG/Samsung/Dupont/Infini/ Granium
C59: NA | D59: LG - Artic White # S006
A60: 17 | B60: Roller Blinds | C60: NA
A61: 18 | B61: Fire Rated Door | C61: NA | D61: Kenwood / Promat
A62: 19 | B62: Aluminium Composite Panel | C62: NA | D62: Eurobond # Bright Silver - ER 101 Red -ER 107 Silver - ER102
A63: 20 | B63: Fabric | C63: NA | D63: Response - HDFC Blue
A64: 21 | B64: Aluminium skirting / chair guard / hat section | C64: NA | D64: Bottomline/ Orno
A65: 23 | B65: Modular Furniture | C65: BIFMA / Green Guard / Green Pro Certification- (Interior products must produce BIFMA M 7.1, E3 / Green Guard Certificate (Sustainability) | D65: AFC Furnitures , PSL and other brands approved by CPC team
B67: Ceiling
A68: 1 | B68: Gypsum Ceiling | C68: Green Pro Certification | D68: Gyproc Saint Gobin : Gypboard Plain Gypboard Fireline Board India Gypsum : Regular Gypsum Board Fire Resistance Gypsum Board USG Boral : Sheetrock Gypsum Board Firebloc Board
A69: 2 | B69: Axiom Trim Channel | C69: Green Pro Certification | D69: Armstrong / USG Boral / India Gypsum
A70: 3 | B70: Metal Ceiling | C70: Green Pro Certification | D70: Armstrong : 5488P1 / Indian Gypsum : Aluminium Ceiling Tiles
A71: 4 | B71: Modular Grid Ceiling | C71: Green Pro Certification | D71: Armstrong -USG Boral : 0.7 NRC
B73: Loose Furniture
B75: Center table , Coffee table. | C75: BIFMA / Green Guard / Green Pro Certification- (Interior products must produce BIFMA M 7.1, E3 / Green Guard Certificate (Sustainability) | D75: As approved by CPC Team
B76: Lounge seating / Sofas / Waiting Area Chair | C76: BIFMA / Green Guard / Green Pro Certification- (Interior products must produce BIFMA M 7.1, E3 / Green Guard Certificate (Sustainability) | D76: As approved by CPC Team
B77: Hardware Items
A78: 1 | B78: Aluminum Section | C78: NA | D78: Jindal / Hindalco / Nalco
A79: 2 | B79: Floor Springs | C79: Environmental Product Declaration is mandetor | D79: Dorma/ Hafele / Ozone / Enox
A80: 3 | B80: Door Closer | C80: Environmental Product Declaration is mandetor | D80: Dorma - Sap code: 66400101 Description: TS 68 Door Closer with Std Arm EN 2/3/4 Silver / Ozone / Enox
A81: 4 | B81: Door Stopper | C81: NA | D81: Dorma - Sap Code: 9113304: Description Door Stop half dome 45mm dia / Ozone / Enox
A82: 5 | B82: Magnetic Door Holder | C82: NA | D82: Dorma - Sap Code: 9112181 : Description: Magnetic Door Holder,satin chrome finish / Ozone / Enox
A83: 6 | B83: Glass Handles | C83: NA | D83: Dorma - Sap code: 9125510 Description: TGD D 350 X 25 S, Satin SS 304 / Ozone / Enox
A84: 7 | B84: Dead Lock (for Flush Door) | C84: NA | D84: Dorma - Sap code: 9120855 Description: 706 Dead Lock, 55mm Backset , SSS, Escutcheons - 01 Pair, EPC TTK Key -60mm Qty / Ozone / Enox
A85: 8 | B85: Dead Lock (for Toilet Door) | C85: NA | D85: Dorma - Sap code: 9120855 Description: 706 Dead Lock, 55mm Backset , SSS, Escutcheons - 01 Pair,, One Side Tumb Turn Other side Coin Privacy Key -60mm / Ozone / Enox
A86: 9 | B86: Door Hinges - Brass | C86: NA | D86: Dorma - sap code 9117214 / Description : BB4330, 5 Kn uckle, 2 Ball bearing butt hinges.Size: 4" x 3" x 3mm Grade SS 304 - Fin ish SSS / Ozone / Enox
A87: 10 | B87: Cabinet Handles | C87: NA | D87: Kitch / Ozone / Enox
A88: 11 | B88: Shutter Hinges | C88: NA | D88: Magnum / Palladium / Haffele / Ozone / Enox
A89: 12 | B89: Latch | C89: NA | D89: Godrej / Tag / Hafele/ Ozone / Enox
... A98: 21 | B98: Screws | C98: NA | D98: GKW / Enox
B100: Paint , Ceiling & Flooring Items
A101: 1 | B101: Acrylic Emulsion Paint | C101: Low VOC or No VOC as per IGBC Norms | D101: Berger / Dulux/Nippon Paints/ Surfa Coats India Limited / AkzoNobel India Ltd
A102: 2 | B102: Plastic Paint | C102: Low VOC or No VOC as per IGBC Norms | D102: Berger / Dulux/Nippon Paints/ Surfa Coats India Limited / AkzoNobel India Ltd
A104: 1 | B104: Digital VAF meter | C104: NA | D104: L&T / Yokins
A105: 2 | B105: RYB Indicators | C105: NA | D105: L&T / Tecknics / Vashno
A106: 3 | B106: Panel tagging | C106: NA | D106: Anodised aluminum / Trafolite black on white with etched capital lettering
A107: 4 | B107: APFC Panel ( Capacitor ) | C107: NA | D107: L&T / Vishay / Malde / Epcos
A108: 5 | B108: AC outdoor power supply box enclosure should be IP66 / IP65 | C108: NA | D108: Devi Polymers / Hensel should be IP66
A109: 6 | B109: HRC Fuses | C109: NA | D109: L&T / Schnieder / Siemens
A110: 7 | B110: Fuse Switch Unit | C110: NA | D110: L&T / Schnieder / Siemens
A111: 8 | B111: Glands | C111: NA | D111: ECG / EMI /Comet
A112: 9 | B112: Lugs | C112: NA | D112: Dowells / Lotus
A113: 10 | B113: Terminals | C113: NA | D113: Essen / Elmex
... A130: 27 | B130: Panel / Cables / DB Tagging | C130: NA | D130: Panel / all DB's / Main power cables should be tagged properly with Anodised aluminum / Trafolite black on white plate / phenolic tagging only will be permitted.
